Workbook

Sheet RESUMEN
C1: c30 | E1: b31
C2: dolares | D2: colones | E2: dolares | F2: colones
B3: 2024 | C3: =+'2024 c30'!Q2992 -> 0 | D3: =+'2024 c30'!P2992 -> 702.68 | E3: =+'2024 b31'!Q2987 -> 32951 | F3: =+'2024 b31'!P2987 -> 99121382
B4: 2025 | E4: =+Table13[[#Totals],[Dolares]] -> 361.2 | F4: =+Table13[[#Totals],[Colones]] -> 74705744
C5: =SUM(C3:C4) -> 0 | D5: =SUM(D3:D4) -> 702.68 | E5: =SUM(E3:E4) -> 33312.2 | F5: =SUM(F3:F4) -> 1.7382713e+08
D8: =+C5+D5/500 -> 1.40536 | F8: =+E5+F5/500 -> 380966.45 | G8: gastos al 6 de junio
G9: gastos de los ultimos 2 meses por actualizar de contabilidad
F10: =+'CIERRE de b31'!C27 -> 333673.35 | G10: proyeccion de cierre
F12: =SUM(F8:F10) -> 714639.8
F14: 35638.26 | G14: en cuentas al 18 de agosto

Sheet CIERRE de b31
B1: ITEM | C1: COSTO | D1: CONTRATISTA | E1: COTIZACIONES
B2: VENTANAS | C2: =30146500/500 -> 60293 | E2: vidrios brenes Europa, Bellavida Eurovista esperando
B3: MANO DE OBRA, con liquidaciones | C3: =10*4200*1.37 -> 57540
B4: CIELOS DE MADERA | C4: =348*110*1.13 -> 43256.4 | E4: Vidal Teca wash wash $110/m2
B5: MUEBLES FIJOS | C5: 42000 | E5: Atos, Vidal, The kitchen
B6: PISOS | C6: =479*(40+15+6) -> 29219 | E6: porcelanato y coralina
B7: JARDINERIA | C7: 15000 | E7: Isaac
B8: LUMINARIAS | C8: =+(1715846+458292)/502 -> 4330.9522 | E8: Ledinside
B9: ACABADOS PINTURA, CIELOS GYPSUM, EMPASTES | C9: =619*15 -> 9285
B10: LOZA SANITARIA Y GRIFERIA | C10: 8960 | E10: Helvex
B11: ELECTRODOMESTICOS | C11: 8000
B12: PISCINA EQUIPOS | C12: 7800 | E12: Smartengineering
B13: AIRES ACONDICIONADOS | C13: =1850*4 -> 7400 | D13: Josue
B14: CERRAMIENTOS | C14: 6350
B15: PUERTAS | C15: =40%*13150 -> 5260 | D15: Vidal
B16: TANQUE DE AGUA Y SISTEMA DE PRESION, mas excavacion | C16: =4200+850 -> 5050 | E16: Smartengineering
B17: ENCHAPES baños | C17: =101*(20+24+5) -> 4949 | E17: porcelanato de 7.5x30cm
B18: PISCINA ENCHAPES | C18: =62*(30+20+6) -> 3472 | E18: porcelanato
B19: PINTURA DE CUBIERTA | C19: 2800
B20: MAMPARAS DE VIDRIO EN BAÑOS | C20: 2500 | D20: Vidrios quiros
B21: HOJALATERIA | C21: =1100000/500 -> 2200 | D21: hector carmona
B22: PLAQUERIA GENERAL | C22: 2152
B23: CERRAJERIA | C23: =14*145 -> 2030
B24: PRECINTAS | C24: 2026
B25: PORTON FRONTAL | C25: 1800
C27: =SUM(C2:C25) -> 333673.35
B29: No hay cochera
B32: =TODAY() -> 45954
B33: =18*7 -> 126
A34: 45781 | B34: =+B32+B33 -> 46080

Sheet 2024 c30
G1: id iguales? | H1: =SUM(B:B) -> 0
G2: id consecutivos? | H2: =SUM(C:C) -> 515
G3: sin precio | H3: =SUM(D:D) -> 2
G4: sin formade pago | H4: =SUM(E:E) -> 76
G5: sin centro de costo | H5: =SUM(F:F) -> 0
B7: id iguales? | C7: id consecutivos? | D7: sin precio | E7: sin formade pago | F7: sin centro de costo | G7: identificador | H7: Fecha | I7: diario | P7: colones | Q7: dolares | R7: Tipo Cambio | S7: Precio en $ | T7: Descripcion | U7: forma de pago | W7: Observaciones
J8: =+IF(I8<10,_xlfn.CONCAT("0",I8),I8) -> 0 | K8: =+YEAR(H8)-2000 -> -100 | L8: =+MONTH(H8) -> 1 | M8: =+DAY(H8) -> 0 | N8: =+IF(L8<10,_xlfn.CONCAT("0",L8),L8) -> 01 | O8: =+IF(M8<10,_xlfn.CONCAT("0",M8),M8) -> 00
J9: =+IF(I9<10,_xlfn.CONCAT("0",I9),I9) -> 0 | K9: =+YEAR(H9)-2000 -> -100 | L9: =+MONTH(H9) -> 1 | M9: =+DAY(H9) -> 0 | N9: =+IF(L9<10,_xlfn.CONCAT("0",L9),L9) -> 01 | O9: =+IF(M9<10,_xlfn.CONCAT("0",M9),M9) -> 00
P10: =SUM(P1:P9) -> 0 | Q10: =SUM(Q1:Q9) -> 0 | R10: =SUM(R1:R9) -> 0 | S10: =SUM(S1:S9) -> 0 | V10: PGE C30
A11: 519 | B11: =IF(G11="-",0,IF(G10=G11,1,0)) -> 0 | C11: =+IF(G11="-",0,IF(I11=I10+1,0,(IF(I11=1,0,1)))) -> 1 | D11: =+IF(AND(P11="",Q11=""),1,0) -> 0 | E11: =IF(U11="",1,0) -> 0 | F11: =IF(V11="",1,0) -> 0 | G11: =IF(H11=0,"-",_xlfn.CONCAT(K11,N11,O11,J11)) -> 24051414 | H11: 45426 | I11: 14 | J11: =+IF(I11<10,_xlfn.CONCAT("0",I11),I11) -> 14 | K11: =+YEAR(H11)-2000 -> 24 | L11: =+MONTH(H11) -> 5 | M11: =+DAY(H11) -> 14 | N11: =+IF(L11<10,_xlfn.CONCAT("0",L11),L11) -> 05 | O11: =+IF(M11<10,_xlfn.CONCAT("0",M11),M11) -> 14 | Q11: 131436 | T11: Helvex - PG-1740 | U11: BacD | V11: PGE C30
J14: =+IF(I14<10,_xlfn.CONCAT("0",I14),I14) -> 0 | K14: =+YEAR(H14)-2000 -> -100 | L14: =+MONTH(H14) -> 1 | M14: =+DAY(H14) -> 0 | N14: =+IF(L14<10,_xlfn.CONCAT("0",L14),L14) -> 01 | O14: =+IF(M14<10,_xlfn.CONCAT("0",M14),M14) -> 00
J15: =+IF(I15<10,_xlfn.CONCAT("0",I15),I15) -> 0 | K15: =+YEAR(H15)-2000 -> -100 | L15: =+MONTH(H15) -> 1 | M15: =+DAY(H15) -> 0 | N15: =+IF(L15<10,_xlfn.CONCAT("0",L15),L15) -> 01 | O15: =+IF(M15<10,_xlfn.CONCAT("0",M15),M15) -> 00
J16: =+IF(I16<10,_xlfn.CONCAT("0",I16),I16) -> 0 | K16: =+YEAR(H16)-2000 -> -100 | L16: =+MONTH(H16) -> 1 | M16: =+DAY(H16) -> 0 | N16: =+IF(L16<10,_xlfn.CONCAT("0",L16),L16) -> 01 | O16: =+IF(M16<10,_xlfn.CONCAT("0",M16),M16) -> 00
J17: =+IF(I17<10,_xlfn.CONCAT("0",I17),I17) -> 0 | K17: =+YEAR(H17)-2000 -> -100 | L17: =+MONTH(H17) -> 1 | M17: =+DAY(H17) -> 0 | N17: =+IF(L17<10,_xlfn.CONCAT("0",L17),L17) -> 01 | O17: =+IF(M17<10,_xlfn.CONCAT("0",M17),M17) -> 00
A18: 295 | B18: =IF(G18="-",0,IF(G17=G18,1,0)) -> 0 | C18: =+IF(G18="-",0,IF(I18=I17+1,0,(IF(I18=1,0,1)))) -> 1 | D18: =+IF(AND(P18="",Q18=""),1,0) -> 0 | E18: =IF(U18="",1,0) -> 0 | F18: =IF(V18="",1,0) -> 0 | G18: =IF(H18=0,"-",_xlfn.CONCAT(K18,N18,O18,J18)) -> 24042602 | H18: 45408 | I18: 2 | J18: =+IF(I18<10,_xlfn.CONCAT("0",I18),I18) -> 02 | K18: =+YEAR(H18)-2000 -> 24 | L18: =+MONTH(H18) -> 4 | M18: =+DAY(H18) -> 26 | N18: =+IF(L18<10,_xlfn.CONCAT("0",L18),L18) -> 04 | O18: =+IF(M18<10,_xlfn.CONCAT("0",M18),M18) -> 26 | Q18: 16588.75 | T18: ATOS Muebles Fijos | U18: BacC | V18: PGE C30
J19: =+IF(I19<10,_xlfn.CONCAT("0",I19),I19) -> 0 | K19: =+YEAR(H19)-2000 -> -100 | L19: =+MONTH(H19) -> 1 | M19: =+DAY(H19) -> 0 | N19: =+IF(L19<10,_xlfn.CONCAT("0",L19),L19) -> 01 | O19: =+IF(M19<10,_xlfn.CONCAT("0",M19),M19) -> 00
J20: =+IF(I20<10,_xlfn.CONCAT("0",I20),I20) -> 0 | K20: =+YEAR(H20)-2000 -> -100 | L20: =+MONTH(H20) -> 1 | M20: =+DAY(H20) -> 0 | N20: =+IF(L20<10,_xlfn.CONCAT("0",L20),L20) -> 01 | O20: =+IF(M20<10,_xlfn.CONCAT("0",M20),M20) -> 00
J21: =+IF(I21<10,_xlfn.CONCAT("0",I21),I21) -> 0 | K21: =+YEAR(H21)-2000 -> -100 | L21: =+MONTH(H21) -> 1 | M21: =+DAY(H21) -> 0 | N21: =+IF(L21<10,_xlfn.CONCAT("0",L21),L21) -> 01 | O21: =+IF(M21<10,_xlfn.CONCAT("0",M21),M21) -> 00
J22: =+IF(I22<10,_xlfn.CONCAT("0",I22),I22) -> 0 | K22: =+YEAR(H22)-2000 -> -100 | L22: =+MONTH(H22) -> 1 | M22: =+DAY(H22) -> 0 | N22: =+IF(L22<10,_xlfn.CONCAT("0",L22),L22) -> 01 | O22: =+IF(M22<10,_xlfn.CONCAT("0",M22),M22) -> 00
J23: =+IF(I23<10,_xlfn.CONCAT("0",I23),I23) -> 0 | K23: =+YEAR(H23)-2000 -> -100 | L23: =+MONTH(H23) -> 1 | M23: =+DAY(H23) -> 0 | N23: =+IF(L23<10,_xlfn.CONCAT("0",L23),L23) -> 01 | O23: =+IF(M23<10,_xlfn.CONCAT("0",M23),M23) -> 00
J24: =+IF(I24<10,_xlfn.CONCAT("0",I24),I24) -> 0 | K24: =+YEAR(H24)-2000 -> -100 | L24: =+MONTH(H24) -> 1 | M24: =+DAY(H24) -> 0 | N24: =+IF(L24<10,_xlfn.CONCAT("0",L24),L24) -> 01 | O24: =+IF(M24<10,_xlfn.CONCAT("0",M24),M24) -> 00
J25: =+IF(I25<10,_xlfn.CONCAT("0",I25),I25) -> 0 | K25: =+YEAR(H25)-2000 -> -100 | L25: =+MONTH(H25) -> 1 | M25: =+DAY(H25) -> 0 | N25: =+IF(L25<10,_xlfn.CONCAT("0",L25),L25) -> 01 | O25: =+IF(M25<10,_xlfn.CONCAT("0",M25),M25) -> 00
A26: 437 | B26: =IF(G26="-",0,IF(G25=G26,1,0)) -> 0 | C26: =+IF(G26="-",0,IF(I26=I25+1,0,(IF(I26=1,0,1)))) -> 1 | D26: =+IF(AND(P26="",Q26=""),1,0) -> 0 | E26: =IF(U26="",1,0) -> 0 | F26: =IF(V26="",1,0) -> 0 | G26: =IF(H26=0,"-",_xlfn.CONCAT(K26,N26,O26,J26)) -> 24050904 | H26: 45421 | I26: 4 | J26: =+IF(I26<10,_xlfn.CONCAT("0",I26),I26) -> 04 | K26: =+YEAR(H26)-2000 -> 24 | L26: =+MONTH(H26) -> 5 | M26: =+DAY(H26) -> 9 | N26: =+IF(L26<10,_xlfn.CONCAT("0",L26),L26) -> 05 | O26: =+IF(M26<10,_xlfn.CONCAT("0",M26),M26) -> 09 | Q26: 10637.71 | T26: Poolmaxx Cancela Contrato de Piscina | U26: DavD | V26: PGE C30
J27: =+IF(I27<10,_xlfn.CONCAT("0",I27),I27) -> 0 | K27: =+YEAR(H27)-2000 -> -100 | L27: =+MONTH(H27) -> 1 | M27: =+DAY(H27) -> 0 | N27: =+IF(L27<10,_xlfn.CONCAT("0",L27),L27) -> 01 | O27: =+IF(M27<10,_xlfn.CONCAT("0",M27),M27) -> 00
J28: =+IF(I28<10,_xlfn.CONCAT("0",I28),I28) -> 0 | K28: =+YEAR(H28)-2000 -> -100 | L28: =+MONTH(H28) -> 1 | M28: =+DAY(H28) -> 0 | N28: =+IF(L28<10,_xlfn.CONCAT("0",L28),L28) -> 01 | O28: =+IF(M28<10,_xlfn.CONCAT("0",M28),M28) -> 00
J29: =+IF(I29<10,_xlfn.CONCAT("0",I29),I29) -> 0 | K29: =+YEAR(H29)-2000 -> -100 | L29: =+MONTH(H29) -> 1 | M29: =+DAY(H29) -> 0 | N29: =+IF(L29<10,_xlfn.CONCAT("0",L29),L29) -> 01 | O29: =+IF(M29<10,_xlfn.CONCAT("0",M29),M29) -> 00
J30: =+IF(I30<10,_xlfn.CONCAT("0",I30),I30) -> 0 | K30: =+YEAR(H30)-2000 -> -100 | L30: =+MONTH(H30) -> 1 | M30: =+DAY(H30) -> 0 | N30: =+IF(L30<10,_xlfn.CONCAT("0",L30),L30) -> 01 | O30: =+IF(M30<10,_xlfn.CONCAT("0",M30),M30) -> 00
J31: =+IF(I31<10,_xlfn.CONCAT("0",I31),I31) -> 0 | K31: =+YEAR(H31)-2000 -> -100 | L31: =+MONTH(H31) -> 1 | M31: =+DAY(H31) -> 0 | N31: =+IF(L31<10,_xlfn.CONCAT("0",L31),L31) -> 01 | O31: =+IF(M31<10,_xlfn.CONCAT("0",M31),M31) -> 00
J32: =+IF(I32<10,_xlfn.CONCAT("0",I32),I32) -> 0 | K32: =+YEAR(H32)-2000 -> -100 | L32: =+MONTH(H32) -> 1 | M32: =+DAY(H32) -> 0 | N32: =+IF(L32<10,_xlfn.CONCAT("0",L32),L32) -> 01 | O32: =+IF(M32<10,_xlfn.CONCAT("0",M32),M32) -> 00
J33: =+IF(I33<10,_xlfn.CONCAT("0",I33),I33) -> 0 | K33: =+YEAR(H33)-2000 -> -100 | L33: =+MONTH(H33) -> 1 | M33: =+DAY(H33) -> 0 | N33: =+IF(L33<10,_xlfn.CONCAT("0",L33),L33) -> 01 | O33: =+IF(M33<10,_xlfn.CONCAT("0",M33),M33) -> 00
J34: =+IF(I34<10,_xlfn.CONCAT("0",I34),I34) -> 0 | K34: =+YEAR(H34)-2000 -> -100 | L34: =+MONTH(H34) -> 1 | M34: =+DAY(H34) -> 0 | N34: =+IF(L34<10,_xlfn.CONCAT("0",L34),L34) -> 01 | O34: =+IF(M34<10,_xlfn.CONCAT("0",M34),M34) -> 00
J35: =+IF(I35<10,_xlfn.CONCAT("0",I35),I35) -> 0 | K35: =+YEAR(H35)-2000 -> -100 | L35: =+MONTH(H35) -> 1 | M35: =+DAY(H35) -> 0 | N35: =+IF(L35<10,_xlfn.CONCAT("0",L35),L35) -> 01 | O35: =+IF(M35<10,_xlfn.CONCAT("0",M35),M35) -> 00
J36: =+IF(I36<10,_xlfn.CONCAT("0",I36),I36) -> 0 | K36: =+YEAR(H36)-2000 -> -100 | L36: =+MONTH(H36) -> 1 | M36: =+DAY(H36) -> 0 | N36: =+IF(L36<10,_xlfn.CONCAT("0",L36),L36) -> 01 | O36: =+IF(M36<10,_xlfn.CONCAT("0",M36),M36) -> 00
J37: =+IF(I37<10,_xlfn.CONCAT("0",I37),I37) -> 0 | K37: =+YEAR(H37)-2000 -> -100 | L37: =+MONTH(H37) -> 1 | M37: =+DAY(H37) -> 0 | N37: =+IF(L37<10,_xlfn.CONCAT("0",L37),L37) -> 01 | O37: =+IF(M37<10,_xlfn.CONCAT("0",M37),M37) -> 00
J38: =+IF(I38<10,_xlfn.CONCAT("0",I38),I38) -> 0 | K38: =+YEAR(H38)-2000 -> -100 | L38: =+MONTH(H38) -> 1 | M38: =+DAY(H38) -> 0 | N38: =+IF(L38<10,_xlfn.CONCAT("0",L38),L38) -> 01 | O38: =+IF(M38<10,_xlfn.CONCAT("0",M38),M38) -> 00
... J40: =+IF(I40<10,_xlfn.CONCAT("0",I40),I40) -> 0 | K40: =+YEAR(H40)-2000 -> -100 | L40: =+MONTH(H40) -> 1 | M40: =+DAY(H40) -> 0 | N40: =+IF(L40<10,_xlfn.CONCAT("0",L40),L40) -> 01 | O40: =+IF(M40<10,_xlfn.CONCAT("0",M40),M40) -> 00
A41: 736 | B41: =IF(G41="-",0,IF(G39=G41,1,0)) -> 0 | C41: =+IF(G41="-",0,IF(I41=I39+1,0,(IF(I41=1,0,1)))) -> 1 | D41: =+IF(AND(P41="",Q41=""),1,0) -> 0 | E41: =IF(U41="",1,0) -> 0 | F41: =IF(V41="",1,0) -> 0 | G41: =IF(H41=0,"-",_xlfn.CONCAT(K41,N41,O41,J41)) -> 24060303 | H41: 45446 | I41: 3 | J41: =+IF(I41<10,_xlfn.CONCAT("0",I41),I41) -> 03 | K41: =+YEAR(H41)-2000 -> 24 | L41: =+MONTH(H41) -> 6 | M41: =+DAY(H41) -> 3 | N41: =+IF(L41<10,_xlfn.CONCAT("0",L41),L41) -> 06 | O41: =+IF(M41<10,_xlfn.CONCAT("0",M41),M41) -> 03 | Q41: 7327.5 | S41: =IFERROR(P41/R41,"") | T41: Atos DE OCCIDENTE SA - pago de muebles c30 | U41: DavD | V41: PGE C30
A42: 134 | B42: =IF(G42="-",0,IF(G41=G42,1,0)) -> 0 | C42: =+IF(G42="-",0,IF(I42=I41+1,0,(IF(I42=1,0,1)))) -> 0 | D42: =+IF(AND(P42="",Q42=""),1,0) -> 0 | E42: =IF(U42="",1,0) -> 0 | F42: =IF(V42="",1,0) -> 0 | G42: =IF(H42=0,"-",_xlfn.CONCAT(K42,N42,O42,J42)) -> 24041001 | H42: 45392 | I42: 1 | J42: =+IF(I42<10,_xlfn.CONCAT("0",I42),I42) -> 01 | K42: =+YEAR(H42)-2000 -> 24 | L42: =+MONTH(H42) -> 4 | M42: =+DAY(H42) -> 10 | N42: =+IF(L42<10,_xlfn.CONCAT("0",L42),L42) -> 04 | O42: =+IF(M42<10,_xlfn.CONCAT("0",M42),M42) -> 10 | Q42: =10109.83*0.7 -> 7076.881 | T42: Bella Vida CR - 70% adelanto ventanas 5ta habitacion | U42: BacD | V42: PGE C30
A43: 199 | B43: =IF(G43="-",0,IF(G42=G43,1,0)) -> 0 | C43: =+IF(G43="-",0,IF(I43=I42+1,0,(IF(I43=1,0,1)))) -> 1 | D43: =+IF(AND(P43="",Q43=""),1,0) -> 0 | E43: =IF(U43="",1,0) -> 0 | F43: =IF(V43="",1,0) -> 0 | G43: =IF(H43=0,"-",_xlfn.CONCAT(K43,N43,O43,J43)) -> 24041606 | H43: 45398 | I43: 6 | J43: =+IF(I43<10,_xlfn.CONCAT("0",I43),I43) -> 06 | K43: =+YEAR(H43)-2000 -> 24 | L43: =+MONTH(H43) -> 4 | M43: =+DAY(H43) -> 16 | N43: =+IF(L43<10,_xlfn.CONCAT("0",L43),L43) -> 04 | O43: =+IF(M43<10,_xlfn.CONCAT("0",M43),M43) -> 16 | Q43: 5796.9 | T43: ECOSISTEMAS SANITARIOS S A - Pago 1 | U43: DavD | V43: PGE C30
A44: 2904 | B44: =IF(G44="-",0,IF(G43=G44,1,0)) -> 0 | C44: =+IF(G44="-",0,IF(I44=I43+1,0,(IF(I44=1,0,1)))) -> 1 | D44: =+IF(AND(P44="",Q44=""),1,0) -> 0 | E44: =IF(U44="",1,0) -> 0 | F44: =IF(V44="",1,0) -> 0 | G44: =IF(H44=0,"-",_xlfn.CONCAT(K44,N44,O44,J44)) -> 24121909 | H44: 45645 | I44: 9 | J44: =+IF(I44<10,_xlfn.CONCAT("0",I44),I44) -> 09 | K44: =+YEAR(H44)-2000 -> 24 | L44: =+MONTH(H44) -> 12 | M44: =+DAY(H44) -> 19 | N44: =+IF(L44<10,_xlfn.CONCAT("0",L44),L44) -> 12 | O44: =+IF(M44<10,_xlfn.CONCAT("0",M44),M44) -> 19 | Q44: 5714.65 | T44: CUBIERTAS INTEGRALES AG LTDA - Cielo Vivo - Cancela C30 | U44: BacD | V44: PGE C30
A45: 1105 | B45: =IF(G45="-",0,IF(G43=G45,1,0)) -> 0 | C45: =+IF(G45="-",0,IF(I45=I43+1,0,(IF(I45=1,0,1)))) -> 1 | D45: =+IF(AND(P45="",Q45=""),1,0) -> 0 | E45: =IF(U45="",1,0) -> 0 | F45: =IF(V45="",1,0) -> 0 | G45: =IF(H45=0,"-",_xlfn.CONCAT(K45,N45,O45,J45)) -> 24070413 | H45: 45477 | I45: 13 | J45: =+IF(I45<10,_xlfn.CONCAT("0",I45),I45) -> 13 | K45: =+YEAR(H45)-2000 -> 24 | L45: =+MONTH(H45) -> 7 | M45: =+DAY(H45) -> 4 | N45: =+IF(L45<10,_xlfn.CONCAT("0",L45),L45) -> 07 | O45: =+IF(M45<10,_xlfn.CONCAT("0",M45),M45) -> 04 | Q45: 5058 | R45: 519 | S45: =IFERROR(P45/R45,"") -> 0 | T45: ATOS DE OCCIDENTE SA - CANCELACIÓN c30 | U45: DavD | V45: PGE C30 | W45: Tipo de Cambio de DaVivienda
A46: 937 | B46: =IF(G46="-",0,IF(G45=G46,1,0)) -> 0 | C46: =+IF(G46="-",0,IF(I46=I45+1,0,(IF(I46=1,0,1)))) -> 1 | D46: =+IF(AND(P46="",Q46=""),1,0) -> 0 | E46: =IF(U46="",1,0) -> 0 | F46: =IF(V46="",1,0) -> 0 | G46: =IF(H46=0,"-",_xlfn.CONCAT(K46,N46,O46,J46)) -> 24062103 | H46: 45464 | I46: 3 | J46: =+IF(I46<10,_xlfn.CONCAT("0",I46),I46) -> 03 | K46: =+YEAR(H46)-2000 -> 24 | L46: =+MONTH(H46) -> 6 | M46: =+DAY(H46) -> 21 | N46: =+IF(L46<10,_xlfn.CONCAT("0",L46),L46) -> 06 | O46: =+IF(M46<10,_xlfn.CONCAT("0",M46),M46) -> 21 | Q46: 4671.43 | S46: =IFERROR(P46/R46,"") | T46: Bella Vida CR Distribuidora SA - Contrato 1 | U46: DavD | V46: PGE C30
A47: 438 | B47: =IF(G47="-",0,IF(G46=G47,1,0)) -> 0 | C47: =+IF(G47="-",0,IF(I47=I46+1,0,(IF(I47=1,0,1)))) -> 1 | D47: =+IF(AND(P47="",Q47=""),1,0) -> 0 | E47: =IF(U47="",1,0) -> 0 | F47: =IF(V47="",1,0) -> 0 | G47: =IF(H47=0,"-",_xlfn.CONCAT(K47,N47,O47,J47)) -> 24050905 | H47: 45421 | I47: 5 | J47: =+IF(I47<10,_xlfn.CONCAT("0",I47),I47) -> 05 | K47: =+YEAR(H47)-2000 -> 24 | L47: =+MONTH(H47) -> 5 | M47: =+DAY(H47) -> 9 | N47: =+IF(L47<10,_xlfn.CONCAT("0",L47),L47) -> 05 | O47: =+IF(M47<10,_xlfn.CONCAT("0",M47),M47) -> 09 | Q47: 4663.5 | T47: Beltran Ingeniería Fact 315 - Alarmas | U47: BacD | V47: PGE C30
A48: 466 | B48: =IF(G48="-",0,IF(G47=G48,1,0)) -> 0 | C48: =+IF(G48="-",0,IF(I48=I47+1,0,(IF(I48=1,0,1)))) -> 1 | D48: =+IF(AND(P48="",Q48=""),1,0) -> 0 | E48: =IF(U48="",1,0) -> 0 | F48: =IF(V48="",1,0) -> 0 | G48: =IF(H48=0,"-",_xlfn.CONCAT(K48,N48,O48,J48)) -> 24051008 | H48: 45422 | I48: 8 | J48: =+IF(I48<10,_xlfn.CONCAT("0",I48),I48) -> 08 | K48: =+YEAR(H48)-2000 -> 24 | L48: =+MONTH(H48) -> 5 | M48: =+DAY(H48) -> 10 | N48: =+IF(L48<10,_xlfn.CONCAT("0",L48),L48) -> 05 | O48: =+IF(M48<10,_xlfn.CONCAT("0",M48),M48) -> 10 | Q48: 4000 | T48: ISAAC FRANCISCO MESEN GUERRERO - CONTRATO DE JARDINERIA, PAGO 2 | U48: DavD | V48: PGE C30
A49: 11 | B49: =IF(G49="-",0,IF(G48=G49,1,0)) -> 0 | C49: =+IF(G49="-",0,IF(I49=I48+1,0,(IF(I49=1,0,1)))) -> 1 | D49: =+IF(AND(P49="",Q49=""),1,0) -> 0 | E49: =IF(U49="",1,0) -> 0 | F49: =IF(V49="",1,0) -> 0 | G49: =IF(H49=0,"-",_xlfn.CONCAT(K49,N49,O49,J49)) -> 24032705 | H49: 45378 | I49: 5 | J49: =+IF(I49<10,_xlfn.CONCAT("0",I49),I49) -> 05 | K49: =+YEAR(H49)-2000 -> 24 | L49: =+MONTH(H49) -> 3 | M49: =+DAY(H49) -> 27 | N49: =+IF(L49<10,_xlfn.CONCAT("0",L49),L49) -> 03 | O49: =+IF(M49<10,_xlfn.CONCAT("0",M49),M49) -> 27 | Q49: 3861.59 | T49: piscina poolmaxx | U49: DavD | V49: PGE C30
A50: 1107 | B50: =IF(G50="-",0,IF(G48=G50,1,0)) -> 0 | C50: =+IF(G50="-",0,IF(I50=I48+1,0,(IF(I50=1,0,1)))) -> 1 | D50: =+IF(AND(P50="",Q50=""),1,0) -> 0 | E50: =IF(U50="",1,0) -> 0 | F50: =IF(V50="",1,0) -> 0 | G50: =IF(H50=0,"-",_xlfn.CONCAT(K50,N50,O50,J50)) -> 24070414 | H50: 45477 | I50: 14 | J50: =+IF(I50<10,_xlfn.CONCAT("0",I50),I50) -> 14 | K50: =+YEAR(H50)-2000 -> 24 | L50: =+MONTH(H50) -> 7 | M50: =+DAY(H50) -> 4 | N50: =+IF(L50<10,_xlfn.CONCAT("0",L50),L50) -> 07 | O50: =+IF(M50<10,_xlfn.CONCAT("0",M50),M50) -> 04 | Q50: 3500 | R50: 519 | S50: =IFERROR(P50/R50,"") -> 0 | T50: Beltran Ingeniería - Cancela Contratos de C30 | U50: DavD | V50: PGE C30 | W50: Tipo de Cambio de DaVivienda
A51: 1181 | B51: =IF(G51="-",0,IF(G50=G51,1,0)) -> 0 | C51: =+IF(G51="-",0,IF(I51=I50+1,0,(IF(I51=1,0,1)))) -> 1 | D51: =+IF(AND(P51="",Q51=""),1,0) -> 0 | E51: =IF(U51="",1,0) -> 0 | F51: =IF(V51="",1,0) -> 0 | G51: =IF(H51=0,"-",_xlfn.CONCAT(K51,N51,O51,J51)) -> 24071110 | H51: 45484 | I51: 10 | J51: =+IF(I51<10,_xlfn.CONCAT("0",I51),I51) -> 10 | K51: =+YEAR(H51)-2000 -> 24 | L51: =+MONTH(H51) -> 7 | M51: =+DAY(H51) -> 11 | N51: =+IF(L51<10,_xlfn.CONCAT("0",L51),L51) -> 07 | O51: =+IF(M51<10,_xlfn.CONCAT("0",M51),M51) -> 11 | Q51: 3500 | S51: =IFERROR(P51/R51,"") | T51: BELTRAN INGENIERIA - Adelanto Regulador de Voltaje | U51: DavD | V51: PGE C30
J52: =+IF(I52<10,_xlfn.CONCAT("0",I52),I52) -> 0 | K52: =+YEAR(H52)-2000 -> -100 | L52: =+MONTH(H52) -> 1 | M52: =+DAY(H52) -> 0 | N52: =+IF(L52<10,_xlfn.CONCAT("0",L52),L52) -> 01 | O52: =+IF(M52<10,_xlfn.CONCAT("0",M52),M52) -> 00
J53: =+IF(I53<10,_xlfn.CONCAT("0",I53),I53) -> 0 | K53: =+YEAR(H53)-2000 -> -100 | L53: =+MONTH(H53) -> 1 | M53: =+DAY(H53) -> 0 | N53: =+IF(L53<10,_xlfn.CONCAT("0",L53),L53) -> 01 | O53: =+IF(M53<10,_xlfn.CONCAT("0",M53),M53) -> 00
J54: =+IF(I54<10,_xlfn.CONCAT("0",I54),I54) -> 0 | K54: =+YEAR(H54)-2000 -> -100 | L54: =+MONTH(H54) -> 1 | M54: =+DAY(H54) -> 0 | N54: =+IF(L54<10,_xlfn.CONCAT("0",L54),L54) -> 01 | O54: =+IF(M54<10,_xlfn.CONCAT("0",M54),M54) -> 00
J55: =+IF(I55<10,_xlfn.CONCAT("0",I55),I55) -> 0 | K55: =+YEAR(H55)-2000 -> -100 | L55: =+MONTH(H55) -> 1 | M55: =+DAY(H55) -> 0 | N55: =+IF(L55<10,_xlfn.CONCAT("0",L55),L55) -> 01 | O55: =+IF(M55<10,_xlfn.CONCAT("0",M55),M55) -> 00
J56: =+IF(I56<10,_xlfn.CONCAT("0",I56),I56) -> 0 | K56: =+YEAR(H56)-2000 -> -100 | L56: =+MONTH(H56) -> 1 | M56: =+DAY(H56) -> 0 | N56: =+IF(L56<10,_xlfn.CONCAT("0",L56),L56) -> 01 | O56: =+IF(M56<10,_xlfn.CONCAT("0",M56),M56) -> 00
J57: =+IF(I57<10,_xlfn.CONCAT("0",I57),I57) -> 0 | K57: =+YEAR(H57)-2000 -> -100 | L57: =+MONTH(H57) -> 1 | M57: =+DAY(H57) -> 0 | N57: =+IF(L57<10,_xlfn.CONCAT("0",L57),L57) -> 01 | O57: =+IF(M57<10,_xlfn.CONCAT("0",M57),M57) -> 00
J58: =+IF(I58<10,_xlfn.CONCAT("0",I58),I58) -> 0 | K58: =+YEAR(H58)-2000 -> -100 | L58: =+MONTH(H58) -> 1 | M58: =+DAY(H58) -> 0 | N58: =+IF(L58<10,_xlfn.CONCAT("0",L58),L58) -> 01 | O58: =+IF(M58<10,_xlfn.CONCAT("0",M58),M58) -> 00
J59: =+IF(I59<10,_xlfn.CONCAT("0",I59),I59) -> 0 | K59: =+YEAR(H59)-2000 -> -100 | L59: =+MONTH(H59) -> 1 | M59: =+DAY(H59) -> 0 | N59: =+IF(L59<10,_xlfn.CONCAT("0",L59),L59) -> 01 | O59: =+IF(M59<10,_xlfn.CONCAT("0",M59),M59) -> 00
J60: =+IF(I60<10,_xlfn.CONCAT("0",I60),I60) -> 0 | K60: =+YEAR(H60)-2000 -> -100 | L60: =+MONTH(H60) -> 1 | M60: =+DAY(H60) -> 0 | N60: =+IF(L60<10,_xlfn.CONCAT("0",L60),L60) -> 01 | O60: =+IF(M60<10,_xlfn.CONCAT("0",M60),M60) -> 00
J61: =+IF(I61<10,_xlfn.CONCAT("0",I61),I61) -> 0 | K61: =+YEAR(H61)-2000 -> -100 | L61: =+MONTH(H61) -> 1 | M61: =+DAY(H61) -> 0 | N61: =+IF(L61<10,_xlfn.CONCAT("0",L61),L61) -> 01 | O61: =+IF(M61<10,_xlfn.CONCAT("0",M61),M61) -> 00
J62: =+IF(I62<10,_xlfn.CONCAT("0",I62),I62) -> 0 | K62: =+YEAR(H62)-2000 -> -100 | L62: =+MONTH(H62) -> 1 | M62: =+DAY(H62) -> 0 | N62: =+IF(L62<10,_xlfn.CONCAT("0",L62),L62) -> 01 | O62: =+IF(M62<10,_xlfn.CONCAT("0",M62),M62) -> 00
J63: =+IF(I63<10,_xlfn.CONCAT("0",I63),I63) -> 0 | K63: =+YEAR(H63)-2000 -> -100 | L63: =+MONTH(H63) -> 1 | M63: =+DAY(H63) -> 0 | N63: =+IF(L63<10,_xlfn.CONCAT("0",L63),L63) -> 01 | O63: =+IF(M63<10,_xlfn.CONCAT("0",M63),M63) -> 00
... J66: =+IF(I66<10,_xlfn.CONCAT("0",I66),I66) -> 0 | K66: =+YEAR(H66)-2000 -> -100 | L66: =+MONTH(H66) -> 1 | M66: =+DAY(H66) -> 0 | N66: =+IF(L66<10,_xlfn.CONCAT("0",L66),L66) -> 01 | O66: =+IF(M66<10,_xlfn.CONCAT("0",M66),M66) -> 00
A67: 2326 | B67: =IF(G67="-",0,IF(G66=G67,1,0)) -> 0 | C67: =+IF(G67="-",0,IF(I67=I66+1,0,(IF(I67=1,0,1)))) -> 1 | D67: =+IF(AND(P67="",Q67=""),1,0) -> 0 | E67: =IF(U67="",1,0) -> 0 | F67: =IF(V67="",1,0) -> 0 | G67: =IF(H67=0,"-",_xlfn.CONCAT(K67,N67,O67,J67)) -> 24102202 | H67: 45587 | I67: 2 | J67: =+IF(I67<10,_xlfn.CONCAT("0",I67),I67) -> 02 | K67: =+YEAR(H67)-2000 -> 24 | L67: =+MONTH(H67) -> 10 | M67: =+DAY(H67) -> 22 | N67: =+IF(L67<10,_xlfn.CONCAT("0",L67),L67) -> 10 | O67: =+IF(M67<10,_xlfn.CONCAT("0",M67),M67) -> 22 | Q67: 2864.6 | T67: Bambu y Maderas SA - c30 deck para portones LD247256 V2 | U67: DavD | V67: PGE C30
J68: =+IF(I68<10,_xlfn.CONCAT("0",I68),I68) -> 0 | K68: =+YEAR(H68)-2000 -> -100 | L68: =+MONTH(H68) -> 1 | M68: =+DAY(H68) -> 0 | N68: =+IF(L68<10,_xlfn.CONCAT("0",L68),L68) -> 01 | O68: =+IF(M68<10,_xlfn.CONCAT("0",M68),M68) -> 00
J69: =+IF(I69<10,_xlfn.CONCAT("0",I69),I69) -> 0 | K69: =+YEAR(H69)-2000 -> -100 | L69: =+MONTH(H69) -> 1 | M69: =+DAY(H69) -> 0 | N69: =+IF(L69<10,_xlfn.CONCAT("0",L69),L69) -> 01 | O69: =+IF(M69<10,_xlfn.CONCAT("0",M69),M69) -> 00 | R69: 495 | S69: =+P69/R69 -> 0
J70: =+IF(I70<10,_xlfn.CONCAT("0",I70),I70) -> 0 | K70: =+YEAR(H70)-2000 -> -100 | L70: =+MONTH(H70) -> 1 | M70: =+DAY(H70) -> 0 | N70: =+IF(L70<10,_xlfn.CONCAT("0",L70),L70) -> 01 | O70: =+IF(M70<10,_xlfn.CONCAT("0",M70),M70) -> 00
A71: 2352 | B71: =IF(G71="-",0,IF(G70=G71,1,0)) -> 0 | C71: =+IF(G71="-",0,IF(I71=I70+1,0,(IF(I71=1,0,1)))) -> 1 | D71: =+IF(AND(P71="",Q71=""),1,0) -> 0 | E71: =IF(U71="",1,0) -> 1 | F71: =IF(V71="",1,0) -> 0 | G71: =IF(H71=0,"-",_xlfn.CONCAT(K71,N71,O71,J71)) -> 24102505 | H71: 45590 | I71: 5 | J71: =+IF(I71<10,_xlfn.CONCAT("0",I71),I71) -> 05 | K71: =+YEAR(H71)-2000 -> 24 | L71: =+MONTH(H71) -> 10 | M71: =+DAY(H71) -> 25 | N71: =+IF(L71<10,_xlfn.CONCAT("0",L71),L71) -> 10 | O71: =+IF(M71<10,_xlfn.CONCAT("0",M71),M71) -> 25 | Q71: 2864.6 | T71: Bambu y Maderas SA - 17,52 M2 Piso Exteriores y transporte | V71: PGE C30
A72: 1721 | B72: =IF(G72="-",0,IF(G71=G72,1,0)) -> 0 | C72: =+IF(G72="-",0,IF(I72=I71+1,0,(IF(I72=1,0,1)))) -> 0 | D72: =+IF(AND(P72="",Q72=""),1,0) -> 0 | E72: =IF(U72="",1,0) -> 0 | F72: =IF(V72="",1,0) -> 0 | G72: =IF(H72=0,"-",_xlfn.CONCAT(K72,N72,O72,J72)) -> 24082606 | H72: 45530 | I72: 6 | J72: =+IF(I72<10,_xlfn.CONCAT("0",I72),I72) -> 06 | K72: =+YEAR(H72)-2000 -> 24 | L72: =+MONTH(H72) -> 8 | M72: =+DAY(H72) -> 26 | N72: =+IF(L72<10,_xlfn.CONCAT("0",L72),L72) -> 08 | O72: =+IF(M72<10,_xlfn.CONCAT("0",M72),M72) -> 26 | Q72: =2850 -> 2850 | S72: =IFERROR(P72/R72,"") | T72: Nimbu Woods SA - Adelanto Puertas y mar | U72: DavD | V72: PGE C30
J73: =+IF(I73<10,_xlfn.CONCAT("0",I73),I73) -> 0 | K73: =+YEAR(H73)-2000 -> -100 | L73: =+MONTH(H73) -> 1 | M73: =+DAY(H73) -> 0 | N73: =+IF(L73<10,_xlfn.CONCAT("0",L73),L73) -> 01 | O73: =+IF(M73<10,_xlfn.CONCAT("0",M73),M73) -> 00
J74: =+IF(I74<10,_xlfn.CONCAT("0",I74),I74) -> 0 | K74: =+YEAR(H74)-2000 -> -100 | L74: =+MONTH(H74) -> 1 | M74: =+DAY(H74) -> 0 | N74: =+IF(L74<10,_xlfn.CONCAT("0",L74),L74) -> 01 | O74: =+IF(M74<10,_xlfn.CONCAT("0",M74),M74) -> 00
J75: =+IF(I75<10,_xlfn.CONCAT("0",I75),I75) -> 0 | K75: =+YEAR(H75)-2000 -> -100 | L75: =+MONTH(H75) -> 1 | M75: =+DAY(H75) -> 0 | N75: =+IF(L75<10,_xlfn.CONCAT("0",L75),L75) -> 01 | O75: =+IF(M75<10,_xlfn.CONCAT("0",M75),M75) -> 00
J76: =+IF(I76<10,_xlfn.CONCAT("0",I76),I76) -> 0 | K76: =+YEAR(H76)-2000 -> -100 | L76: =+MONTH(H76) -> 1 | M76: =+DAY(H76) -> 0 | N76: =+IF(L76<10,_xlfn.CONCAT("0",L76),L76) -> 01 | O76: =+IF(M76<10,_xlfn.CONCAT("0",M76),M76) -> 00
J77: =+IF(I77<10,_xlfn.CONCAT("0",I77),I77) -> 0 | K77: =+YEAR(H77)-2000 -> -100 | L77: =+MONTH(H77) -> 1 | M77: =+DAY(H77) -> 0 | N77: =+IF(L77<10,_xlfn.CONCAT("0",L77),L77) -> 01 | O77: =+IF(M77<10,_xlfn.CONCAT("0",M77),M77) -> 00
J78: =+IF(I78<10,_xlfn.CONCAT("0",I78),I78) -> 0 | K78: =+YEAR(H78)-2000 -> -100 | L78: =+MONTH(H78) -> 1 | M78: =+DAY(H78) -> 0 | N78: =+IF(L78<10,_xlfn.CONCAT("0",L78),L78) -> 01 | O78: =+IF(M78<10,_xlfn.CONCAT("0",M78),M78) -> 00
J79: =+IF(I79<10,_xlfn.CONCAT("0",I79),I79) -> 0 | K79: =+YEAR(H79)-2000 -> -100 | L79: =+MONTH(H79) -> 1 | M79: =+DAY(H79) -> 0 | N79: =+IF(L79<10,_xlfn.CONCAT("0",L79),L79) -> 01 | O79: =+IF(M79<10,_xlfn.CONCAT("0",M79),M79) -> 00
A80: 514 | B80: =IF(G80="-",0,IF(G79=G80,1,0)) -> 0 | C80: =+IF(G80="-",0,IF(I80=I79+1,0,(IF(I80=1,0,1)))) -> 1 | D80: =+IF(AND(P80="",Q80=""),1,0) -> 0 | E80: =IF(U80="",1,0) -> 0 | F80: =IF(V80="",1,0) -> 0 | G80: =IF(H80=0,"-",_xlfn.CONCAT(K80,N80,O80,J80)) -> 24051409 | H80: 45426 | I80: 9 | J80: =+IF(I80<10,_xlfn.CONCAT("0",I80),I80) -> 09 | K80: =+YEAR(H80)-2000 -> 24 | L80: =+MONTH(H80) -> 5 | M80: =+DAY(H80) -> 14 | N80: =+IF(L80<10,_xlfn.CONCAT("0",L80),L80) -> 05 | O80: =+IF(M80<10,_xlfn.CONCAT("0",M80),M80) -> 14 | Q80: 2768.5 | T80: LED INSIDE SRL | U80: BacD | V80: PGE C30
J81: =+IF(I81<10,_xlfn.CONCAT("0",I81),I81) -> 0 | K81: =+YEAR(H81)-2000 -> -100 | L81: =+MONTH(H81) -> 1 | M81: =+DAY(H81) -> 0 | N81: =+IF(L81<10,_xlfn.CONCAT("0",L81),L81) -> 01 | O81: =+IF(M81<10,_xlfn.CONCAT("0",M81),M81) -> 00
J82: =+IF(I82<10,_xlfn.CONCAT("0",I82),I82) -> 0 | K82: =+YEAR(H82)-2000 -> -100 | L82: =+MONTH(H82) -> 1 | M82: =+DAY(H82) -> 0 | N82: =+IF(L82<10,_xlfn.CONCAT("0",L82),L82) -> 01 | O82: =+IF(M82<10,_xlfn.CONCAT("0",M82),M82) -> 00
J83: =+IF(I83<10,_xlfn.CONCAT("0",I83),I83) -> 0 | K83: =+YEAR(H83)-2000 -> -100 | L83: =+MONTH(H83) -> 1 | M83: =+DAY(H83) -> 0 | N83: =+IF(L83<10,_xlfn.CONCAT("0",L83),L83) -> 01 | O83: =+IF(M83<10,_xlfn.CONCAT("0",M83),M83) -> 00
J84: =+IF(I84<10,_xlfn.CONCAT("0",I84),I84) -> 0 | K84: =+YEAR(H84)-2000 -> -100 | L84: =+MONTH(H84) -> 1 | M84: =+DAY(H84) -> 0 | N84: =+IF(L84<10,_xlfn.CONCAT("0",L84),L84) -> 01 | O84: =+IF(M84<10,_xlfn.CONCAT("0",M84),M84) -> 00
J85: =+IF(I85<10,_xlfn.CONCAT("0",I85),I85) -> 0 | K85: =+YEAR(H85)-2000 -> -100 | L85: =+MONTH(H85) -> 1 | M85: =+DAY(H85) -> 0 | N85: =+IF(L85<10,_xlfn.CONCAT("0",L85),L85) -> 01 | O85: =+IF(M85<10,_xlfn.CONCAT("0",M85),M85) -> 00
J86: =+IF(I86<10,_xlfn.CONCAT("0",I86),I86) -> 0 | K86: =+YEAR(H86)-2000 -> -100 | L86: =+MONTH(H86) -> 1 | M86: =+DAY(H86) -> 0 | N86: =+IF(L86<10,_xlfn.CONCAT("0",L86),L86) -> 01 | O86: =+IF(M86<10,_xlfn.CONCAT("0",M86),M86) -> 00
J87: =+IF(I87<10,_xlfn.CONCAT("0",I87),I87) -> 0 | K87: =+YEAR(H87)-2000 -> -100 | L87: =+MONTH(H87) -> 1 | M87: =+DAY(H87) -> 0 | N87: =+IF(L87<10,_xlfn.CONCAT("0",L87),L87) -> 01 | O87: =+IF(M87<10,_xlfn.CONCAT("0",M87),M87) -> 00
J88: =+IF(I88<10,_xlfn.CONCAT("0",I88),I88) -> 0 | K88: =+YEAR(H88)-2000 -> -100 | L88: =+MONTH(H88) -> 1 | M88: =+DAY(H88) -> 0 | N88: =+IF(L88<10,_xlfn.CONCAT("0",L88),L88) -> 01 | O88: =+IF(M88<10,_xlfn.CONCAT("0",M88),M88) -> 00
J89: =+IF(I89<10,_xlfn.CONCAT("0",I89),I89) -> 0 | K89: =+YEAR(H89)-2000 -> -100 | L89: =+MONTH(H89) -> 1 | M89: =+DAY(H89) -> 0 | N89: =+IF(L89<10,_xlfn.CONCAT("0",L89),L89) -> 01 | O89: =+IF(M89<10,_xlfn.CONCAT("0",M89),M89) -> 00
J90: =+IF(I90<10,_xlfn.CONCAT("0",I90),I90) -> 0 | K90: =+YEAR(H90)-2000 -> -100 | L90: =+MONTH(H90) -> 1 | M90: =+DAY(H90) -> 0 | N90: =+IF(L90<10,_xlfn.CONCAT("0",L90),L90) -> 01 | O90: =+IF(M90<10,_xlfn.CONCAT("0",M90),M90) -> 00
J91: =+IF(I91<10,_xlfn.CONCAT("0",I91),I91) -> 0 | K91: =+YEAR(H91)-2000 -> -100 | L91: =+MONTH(H91) -> 1 | M91: =+DAY(H91) -> 0 | N91: =+IF(L91<10,_xlfn.CONCAT("0",L91),L91) -> 01 | O91: =+IF(M91<10,_xlfn.CONCAT("0",M91),M91) -> 00
A92: 96 | B92: =IF(G92="-",0,IF(G91=G92,1,0)) -> 0 | C92: =+IF(G92="-",0,IF(I92=I91+1,0,(IF(I92=1,0,1)))) -> 1 | D92: =+IF(AND(P92="",Q92=""),1,0) -> 0 | E92: =IF(U92="",1,0) -> 0 | F92: =IF(V92="",1,0) -> 0 | G92: =IF(H92=0,"-",_xlfn.CONCAT(K92,N92,O92,J92)) -> 24040504 | H92: 45387 | I92: 4 | J92: =+IF(I92<10,_xlfn.CONCAT("0",I92),I92) -> 04 | K92: =+YEAR(H92)-2000 -> 24 | L92: =+MONTH(H92) -> 4 | M92: =+DAY(H92) -> 5 | N92: =+IF(L92<10,_xlfn.CONCAT("0",L92),L92) -> 04 | O92: =+IF(M92<10,_xlfn.CONCAT("0",M92),M92) -> 05 | Q92: 2726.68 | T92: HIDROTECNOLOGIA SOSTENIBLE HID ROTECO S.A #1331 | U92: BacD | V92: PGE C30
J93: =+IF(I93<10,_xlfn.CONCAT("0",I93),I93) -> 0 | K93: =+YEAR(H93)-2000 -> -100 | L93: =+MONTH(H93) -> 1 | M93: =+DAY(H93) -> 0 | N93: =+IF(L93<10,_xlfn.CONCAT("0",L93),L93) -> 01 | O93: =+IF(M93<10,_xlfn.CONCAT("0",M93),M93) -> 00
J94: =+IF(I94<10,_xlfn.CONCAT("0",I94),I94) -> 0 | K94: =+YEAR(H94)-2000 -> -100 | L94: =+MONTH(H94) -> 1 | M94: =+DAY(H94) -> 0 | N94: =+IF(L94<10,_xlfn.CONCAT("0",L94),L94) -> 01 | O94: =+IF(M94<10,_xlfn.CONCAT("0",M94),M94) -> 00
J95: =+IF(I95<10,_xlfn.CONCAT("0",I95),I95) -> 0 | K95: =+YEAR(H95)-2000 -> -100 | L95: =+MONTH(H95) -> 1 | M95: =+DAY(H95) -> 0 | N95: =+IF(L95<10,_xlfn.CONCAT("0",L95),L95) -> 01 | O95: =+IF(M95<10,_xlfn.CONCAT("0",M95),M95) -> 00
A96: 936 | B96: =IF(G96="-",0,IF(G95=G96,1,0)) -> 0 | C96: =+IF(G96="-",0,IF(I96=I95+1,0,(IF(I96=1,0,1)))) -> 1 | D96: =+IF(AND(P96="",Q96=""),1,0) -> 0 | E96: =IF(U96="",1,0) -> 0 | F96: =IF(V96="",1,0) -> 0 | G96: =IF(H96=0,"-",_xlfn.CONCAT(K96,N96,O96,J96)) -> 24062102 | H96: 45464 | I96: 2 | J96: =+IF(I96<10,_xlfn.CONCAT("0",I96),I96) -> 02 | K96: =+YEAR(H96)-2000 -> 24 | L96: =+MONTH(H96) -> 6 | M96: =+DAY(H96) -> 21 | N96: =+IF(L96<10,_xlfn.CONCAT("0",L96),L96) -> 06 | O96: =+IF(M96<10,_xlfn.CONCAT("0",M96),M96) -> 21 | Q96: 2367.36 | S96: =IFERROR(P96/R96,"") | T96: Bella Vida CR Distribuidora SA - Contrato 2 | U96: DavD | V96: PGE C30
J97: =+IF(I97<10,_xlfn.CONCAT("0",I97),I97) -> 0 | K97: =+YEAR(H97)-2000 -> -100 | L97: =+MONTH(H97) -> 1 | M97: =+DAY(H97) -> 0 | N97: =+IF(L97<10,_xlfn.CONCAT("0",L97),L97) -> 01 | O97: =+IF(M97<10,_xlfn.CONCAT("0",M97),M97) -> 00
J98: =+IF(I98<10,_xlfn.CONCAT("0",I98),I98) -> 0 | K98: =+YEAR(H98)-2000 -> -100 | L98: =+MONTH(H98) -> 1 | M98: =+DAY(H98) -> 0 | N98: =+IF(L98<10,_xlfn.CONCAT("0",L98),L98) -> 01 | O98: =+IF(M98<10,_xlfn.CONCAT("0",M98),M98) -> 00
J99: =+IF(I99<10,_xlfn.CONCAT("0",I99),I99) -> 0 | K99: =+YEAR(H99)-2000 -> -100 | L99: =+MONTH(H99) -> 1 | M99: =+DAY(H99) -> 0 | N99: =+IF(L99<10,_xlfn.CONCAT("0",L99),L99) -> 01 | O99: =+IF(M99<10,_xlfn.CONCAT("0",M99),M99) -> 00
A100: 465 | B100: =IF(G100="-",0,IF(G99=G100,1,0)) -> 0 | C100: =+IF(G100="-",0,IF(I100=I99+1,0,(IF(I100=1,0,1)))) -> 1 | D100: =+IF(AND(P100="",Q100=""),1,0) -> 0 | E100: =IF(U100="",1,0) -> 0 | F100: =IF(V100="",1,0) -> 0 | G100: =IF(H100=0,"-",_xlfn.CONCAT(K100,N100,O100,J100)) -> 24051007 | H100: 45422 | I100: 7 | J100: =+IF(I100<10,_xlfn.CONCAT("0",I100),I100) -> 07 | K100: =+YEAR(H100)-2000 -> 24 | L100: =+MONTH(H100) -> 5 | M100: =+DAY(H100) -> 10 | N100: =+IF(L100<10,_xlfn.CONCAT("0",L100),L100) -> 05 | O100: =+IF(M100<10,_xlfn.CONCAT("0",M100),M100) -> 10 | Q100: 2330.23 | T100: HELVEX - PL741132 CASA PLAYA GRANDE C30 | U100: DavD | V100: PGE C30
J101: =+IF(I101<10,_xlfn.CONCAT("0",I101),I101) -> 0 | K101: =+YEAR(H101)-2000 -> -100 | L101: =+MONTH(H101) -> 1 | M101: =+DAY(H101) -> 0 | N101: =+IF(L101<10,_xlfn.CONCAT("0",L101),L101) -> 01 | O101: =+IF(M101<10,_xlfn.CONCAT("0",M101),M101) -> 00
A102: 1109 | B102: =IF(G102="-",0,IF(G100=G102,1,0)) -> 0 | C102: =+IF(G102="-",0,IF(I102=I100+1,0,(IF(I102=1,0,1)))) -> 1 | D102: =+IF(AND(P102="",Q102=""),1,0) -> 0 | E102: =IF(U102="",1,0) -> 0 | F102: =IF(V102="",1,0) -> 0 | G102: =IF(H102=0,"-",_xlfn.CONCAT(K102,N102,O102,J102)) -> 24070415 | H102: 45477 | I102: 15 | J102: =+IF(I102<10,_xlfn.CONCAT("0",I102),I102) -> 15 | K102: =+YEAR(H102)-2000 -> 24 | L102: =+MONTH(H102) -> 7 | M102: =+DAY(H102) -> 4 | N102: =+IF(L102<10,_xlfn.CONCAT("0",L102),L102) -> 07 | O102: =+IF(M102<10,_xlfn.CONCAT("0",M102),M102) -> 04 | Q102: 2169.6 | R102: 519 | S102: =IFERROR(P102/R102,"") -> 0 | T102: Nimbu Woods - Adelanto Muebles bajo escaleras | U102: DavD | V102: PGE C30 | W102: Tipo de Cambio de DaVivienda
A103: 1568 | B103: =IF(G103="-",0,IF(G102=G103,1,0)) -> 0 | C103: =+IF(G103="-",0,IF(I103=I102+1,0,(IF(I103=1,0,1)))) -> 0 | D103: =+IF(AND(P103="",Q103=""),1,0) -> 0 | E103: =IF(U103="",1,0) -> 0 | F103: =IF(V103="",1,0) -> 0 | G103: =IF(H103=0,"-",_xlfn.CONCAT(K103,N103,O103,J103)) -> 24081401 | H103: 45518 | I103: 1 | J103: =+IF(I103<10,_xlfn.CONCAT("0",I103),I103) -> 01 | K103: =+YEAR(H103)-2000 -> 24 | L103: =+MONTH(H103) -> 8 | M103: =+DAY(H103) -> 14 | N103: =+IF(L103<10,_xlfn.CONCAT("0",L103),L103) -> 08 | O103: =+IF(M103<10,_xlfn.CONCAT("0",M103),M103) -> 14 | Q103: 2139.6 | S103: =IFERROR(P103/R103,"") | T103: Nimbu Woods SA - Adelanto Instalación de Puertas | U103: DavD | V103: PGE C30
J104: =+IF(I104<10,_xlfn.CONCAT("0",I104),I104) -> 0 | K104: =+YEAR(H104)-2000 -> -100 | L104: =+MONTH(H104) -> 1 | M104: =+DAY(H104) -> 0 | N104: =+IF(L104<10,_xlfn.CONCAT("0",L104),L104) -> 01 | O104: =+IF(M104<10,_xlfn.CONCAT("0",M104),M104) -> 00
J105: =+IF(I105<10,_xlfn.CONCAT("0",I105),I105) -> 0 | K105: =+YEAR(H105)-2000 -> -100 | L105: =+MONTH(H105) -> 1 | M105: =+DAY(H105) -> 0 | N105: =+IF(L105<10,_xlfn.CONCAT("0",L105),L105) -> 01 | O105: =+IF(M105<10,_xlfn.CONCAT("0",M105),M105) -> 00
J106: =+IF(I106<10,_xlfn.CONCAT("0",I106),I106) -> 0 | K106: =+YEAR(H106)-2000 -> -100 | L106: =+MONTH(H106) -> 1 | M106: =+DAY(H106) -> 0 | N106: =+IF(L106<10,_xlfn.CONCAT("0",L106),L106) -> 01 | O106: =+IF(M106<10,_xlfn.CONCAT("0",M106),M106) -> 00
...

Sheet 2024 b31
G1: id iguales? | H1: =SUM(B:B) -> 0
G2: id consecutivos? | H2: =SUM(C:C) -> 219
G3: sin precio | H3: =SUM(D:D) -> #REF!
G4: sin formade pago | H4: =SUM(E:E) -> 93
G5: sin centro de costo | H5: =SUM(F:F) -> 0
B7: id iguales? | C7: id consecutivos? | D7: sin precio | E7: sin formade pago | F7: sin centro de costo | G7: identificador | H7: Fecha | I7: diario | P7: colones | Q7: dolares | R7: Tipo Cambio | S7: Precio en $ | T7: Descripcion | U7: forma de pago | W7: Observaciones
J8: =+IF(I8<10,_xlfn.CONCAT("0",I8),I8) -> 0 | K8: =+YEAR(H8)-2000 -> -100 | L8: =+MONTH(H8) -> 1 | M8: =+DAY(H8) -> 0 | N8: =+IF(L8<10,_xlfn.CONCAT("0",L8),L8) -> 01 | O8: =+IF(M8<10,_xlfn.CONCAT("0",M8),M8) -> 00
J9: =+IF(I9<10,_xlfn.CONCAT("0",I9),I9) -> 0 | K9: =+YEAR(H9)-2000 -> -100 | L9: =+MONTH(H9) -> 1 | M9: =+DAY(H9) -> 0 | N9: =+IF(L9<10,_xlfn.CONCAT("0",L9),L9) -> 01 | O9: =+IF(M9<10,_xlfn.CONCAT("0",M9),M9) -> 00
J10: =+IF(I10<10,_xlfn.CONCAT("0",I10),I10) -> 0 | K10: =+YEAR(H10)-2000 -> -100 | L10: =+MONTH(H10) -> 1 | M10: =+DAY(H10) -> 0 | N10: =+IF(L10<10,_xlfn.CONCAT("0",L10),L10) -> 01 | O10: =+IF(M10<10,_xlfn.CONCAT("0",M10),M10) -> 00
J11: =+IF(I11<10,_xlfn.CONCAT("0",I11),I11) -> 0 | K11: =+YEAR(H11)-2000 -> -100 | L11: =+MONTH(H11) -> 1 | M11: =+DAY(H11) -> 0 | N11: =+IF(L11<10,_xlfn.CONCAT("0",L11),L11) -> 01 | O11: =+IF(M11<10,_xlfn.CONCAT("0",M11),M11) -> 00
A12: 6 | H12: 45377 | Q12: 3 | T12: comision | U12: DavD | V12: PGE B31
A13: 5 | H13: 45377 | Q13: 239.15 | T13: deposito de garantia coopeguanacaste | U13: DavD | V13: PGE B31
J14: =+IF(I14<10,_xlfn.CONCAT("0",I14),I14) -> 0 | K14: =+YEAR(H14)-2000 -> -100 | L14: =+MONTH(H14) -> 1 | M14: =+DAY(H14) -> 0 | N14: =+IF(L14<10,_xlfn.CONCAT("0",L14),L14) -> 01 | O14: =+IF(M14<10,_xlfn.CONCAT("0",M14),M14) -> 00
J15: =+IF(I15<10,_xlfn.CONCAT("0",I15),I15) -> 0 | K15: =+YEAR(H15)-2000 -> -100 | L15: =+MONTH(H15) -> 1 | M15: =+DAY(H15) -> 0 | N15: =+IF(L15<10,_xlfn.CONCAT("0",L15),L15) -> 01 | O15: =+IF(M15<10,_xlfn.CONCAT("0",M15),M15) -> 00
J16: =+IF(I16<10,_xlfn.CONCAT("0",I16),I16) -> 0 | K16: =+YEAR(H16)-2000 -> -100 | L16: =+MONTH(H16) -> 1 | M16: =+DAY(H16) -> 0 | N16: =+IF(L16<10,_xlfn.CONCAT("0",L16),L16) -> 01 | O16: =+IF(M16<10,_xlfn.CONCAT("0",M16),M16) -> 00
J17: =+IF(I17<10,_xlfn.CONCAT("0",I17),I17) -> 0 | K17: =+YEAR(H17)-2000 -> -100 | L17: =+MONTH(H17) -> 1 | M17: =+DAY(H17) -> 0 | N17: =+IF(L17<10,_xlfn.CONCAT("0",L17),L17) -> 01 | O17: =+IF(M17<10,_xlfn.CONCAT("0",M17),M17) -> 00
J18: =+IF(I18<10,_xlfn.CONCAT("0",I18),I18) -> 0 | K18: =+YEAR(H18)-2000 -> -100 | L18: =+MONTH(H18) -> 1 | M18: =+DAY(H18) -> 0 | N18: =+IF(L18<10,_xlfn.CONCAT("0",L18),L18) -> 01 | O18: =+IF(M18<10,_xlfn.CONCAT("0",M18),M18) -> 00
J19: =+IF(I19<10,_xlfn.CONCAT("0",I19),I19) -> 0 | K19: =+YEAR(H19)-2000 -> -100 | L19: =+MONTH(H19) -> 1 | M19: =+DAY(H19) -> 0 | N19: =+IF(L19<10,_xlfn.CONCAT("0",L19),L19) -> 01 | O19: =+IF(M19<10,_xlfn.CONCAT("0",M19),M19) -> 00
J20: =+IF(I20<10,_xlfn.CONCAT("0",I20),I20) -> 0 | K20: =+YEAR(H20)-2000 -> -100 | L20: =+MONTH(H20) -> 1 | M20: =+DAY(H20) -> 0 | N20: =+IF(L20<10,_xlfn.CONCAT("0",L20),L20) -> 01 | O20: =+IF(M20<10,_xlfn.CONCAT("0",M20),M20) -> 00
J21: =+IF(I21<10,_xlfn.CONCAT("0",I21),I21) -> 0 | K21: =+YEAR(H21)-2000 -> -100 | L21: =+MONTH(H21) -> 1 | M21: =+DAY(H21) -> 0 | N21: =+IF(L21<10,_xlfn.CONCAT("0",L21),L21) -> 01 | O21: =+IF(M21<10,_xlfn.CONCAT("0",M21),M21) -> 00
J22: =+IF(I22<10,_xlfn.CONCAT("0",I22),I22) -> 0 | K22: =+YEAR(H22)-2000 -> -100 | L22: =+MONTH(H22) -> 1 | M22: =+DAY(H22) -> 0 | N22: =+IF(L22<10,_xlfn.CONCAT("0",L22),L22) -> 01 | O22: =+IF(M22<10,_xlfn.CONCAT("0",M22),M22) -> 00
J23: =+IF(I23<10,_xlfn.CONCAT("0",I23),I23) -> 0 | K23: =+YEAR(H23)-2000 -> -100 | L23: =+MONTH(H23) -> 1 | M23: =+DAY(H23) -> 0 | N23: =+IF(L23<10,_xlfn.CONCAT("0",L23),L23) -> 01 | O23: =+IF(M23<10,_xlfn.CONCAT("0",M23),M23) -> 00
J24: =+IF(I24<10,_xlfn.CONCAT("0",I24),I24) -> 0 | K24: =+YEAR(H24)-2000 -> -100 | L24: =+MONTH(H24) -> 1 | M24: =+DAY(H24) -> 0 | N24: =+IF(L24<10,_xlfn.CONCAT("0",L24),L24) -> 01 | O24: =+IF(M24<10,_xlfn.CONCAT("0",M24),M24) -> 00
J25: =+IF(I25<10,_xlfn.CONCAT("0",I25),I25) -> 0 | K25: =+YEAR(H25)-2000 -> -100 | L25: =+MONTH(H25) -> 1 | M25: =+DAY(H25) -> 0 | N25: =+IF(L25<10,_xlfn.CONCAT("0",L25),L25) -> 01 | O25: =+IF(M25<10,_xlfn.CONCAT("0",M25),M25) -> 00
... J68: =+IF(I68<10,_xlfn.CONCAT("0",I68),I68) -> 0 | K68: =+YEAR(H68)-2000 -> -100 | L68: =+MONTH(H68) -> 1 | M68: =+DAY(H68) -> 0 | N68: =+IF(L68<10,_xlfn.CONCAT("0",L68),L68) -> 01 | O68: =+IF(M68<10,_xlfn.CONCAT("0",M68),M68) -> 00
A69: 62 | B69: =IF(G69="-",0,IF(G68=G69,1,0)) -> 0 | C69: =+IF(G69="-",0,IF(I69=I68+1,0,(IF(I69=1,0,1)))) -> 0 | D69: =+IF(AND(P69="",Q69=""),1,0) -> 0 | E69: =IF(U69="",1,0) -> 0 | F69: =IF(V69="",1,0) -> 0 | G69: =IF(H69=0,"-",_xlfn.CONCAT(K69,N69,O69,J69)) -> 24040101 | H69: 45383 | I69: 1 | J69: =+IF(I69<10,_xlfn.CONCAT("0",I69),I69) -> 01 | K69: =+YEAR(H69)-2000 -> 24 | L69: =+MONTH(H69) -> 4 | M69: =+DAY(H69) -> 1 | N69: =+IF(L69<10,_xlfn.CONCAT("0",L69),L69) -> 04 | O69: =+IF(M69<10,_xlfn.CONCAT("0",M69),M69) -> 01 | P69: 550000 | R69: 495 | S69: =+P69/R69 -> 1111.1111 | T69: Evelio - Herramienta y equipo de evelio CR80010200009565415850 | U69: DavD | V69: PGE B31
A70: 63 | B70: =IF(G70="-",0,IF(G69=G70,1,0)) -> 0 | C70: =+IF(G70="-",0,IF(I70=I69+1,0,(IF(I70=1,0,1)))) -> 0 | D70: =+IF(AND(P70="",Q70=""),1,0) -> 0 | E70: =IF(U70="",1,0) -> 0 | F70: =IF(V70="",1,0) -> 0 | G70: =IF(H70=0,"-",_xlfn.CONCAT(K70,N70,O70,J70)) -> 24040102 | H70: 45383 | I70: 2 | J70: =+IF(I70<10,_xlfn.CONCAT("0",I70),I70) -> 02 | K70: =+YEAR(H70)-2000 -> 24 | L70: =+MONTH(H70) -> 4 | M70: =+DAY(H70) -> 1 | N70: =+IF(L70<10,_xlfn.CONCAT("0",L70),L70) -> 04 | O70: =+IF(M70<10,_xlfn.CONCAT("0",M70),M70) -> 01 | Q70: 3 | T70: comision | U70: DavD | V70: PGE B31
J71: =+IF(I71<10,_xlfn.CONCAT("0",I71),I71) -> 0 | K71: =+YEAR(H71)-2000 -> -100 | L71: =+MONTH(H71) -> 1 | M71: =+DAY(H71) -> 0 | N71: =+IF(L71<10,_xlfn.CONCAT("0",L71),L71) -> 01 | O71: =+IF(M71<10,_xlfn.CONCAT("0",M71),M71) -> 00
J72: =+IF(I72<10,_xlfn.CONCAT("0",I72),I72) -> 0 | K72: =+YEAR(H72)-2000 -> -100 | L72: =+MONTH(H72) -> 1 | M72: =+DAY(H72) -> 0 | N72: =+IF(L72<10,_xlfn.CONCAT("0",L72),L72) -> 01 | O72: =+IF(M72<10,_xlfn.CONCAT("0",M72),M72) -> 00
J73: =+IF(I73<10,_xlfn.CONCAT("0",I73),I73) -> 0 | K73: =+YEAR(H73)-2000 -> -100 | L73: =+MONTH(H73) -> 1 | M73: =+DAY(H73) -> 0 | N73: =+IF(L73<10,_xlfn.CONCAT("0",L73),L73) -> 01 | O73: =+IF(M73<10,_xlfn.CONCAT("0",M73),M73) -> 00
J74: =+IF(I74<10,_xlfn.CONCAT("0",I74),I74) -> 0 | K74: =+YEAR(H74)-2000 -> -100 | L74: =+MONTH(H74) -> 1 | M74: =+DAY(H74) -> 0 | N74: =+IF(L74<10,_xlfn.CONCAT("0",L74),L74) -> 01 | O74: =+IF(M74<10,_xlfn.CONCAT("0",M74),M74) -> 00
J75: =+IF(I75<10,_xlfn.CONCAT("0",I75),I75) -> 0 | K75: =+YEAR(H75)-2000 -> -100 | L75: =+MONTH(H75) -> 1 | M75: =+DAY(H75) -> 0 | N75: =+IF(L75<10,_xlfn.CONCAT("0",L75),L75) -> 01 | O75: =+IF(M75<10,_xlfn.CONCAT("0",M75),M75) -> 00
J76: =+IF(I76<10,_xlfn.CONCAT("0",I76),I76) -> 0 | K76: =+YEAR(H76)-2000 -> -100 | L76: =+MONTH(H76) -> 1 | M76: =+DAY(H76) -> 0 | N76: =+IF(L76<10,_xlfn.CONCAT("0",L76),L76) -> 01 | O76: =+IF(M76<10,_xlfn.CONCAT("0",M76),M76) -> 00
J77: =+IF(I77<10,_xlfn.CONCAT("0",I77),I77) -> 0 | K77: =+YEAR(H77)-2000 -> -100 | L77: =+MONTH(H77) -> 1 | M77: =+DAY(H77) -> 0 | N77: =+IF(L77<10,_xlfn.CONCAT("0",L77),L77) -> 01 | O77: =+IF(M77<10,_xlfn.CONCAT("0",M77),M77) -> 00
J78: =+IF(I78<10,_xlfn.CONCAT("0",I78),I78) -> 0 | K78: =+YEAR(H78)-2000 -> -100 | L78: =+MONTH(H78) -> 1 | M78: =+DAY(H78) -> 0 | N78: =+IF(L78<10,_xlfn.CONCAT("0",L78),L78) -> 01 | O78: =+IF(M78<10,_xlfn.CONCAT("0",M78),M78) -> 00
J79: =+IF(I79<10,_xlfn.CONCAT("0",I79),I79) -> 0 | K79: =+YEAR(H79)-2000 -> -100 | L79: =+MONTH(H79) -> 1 | M79: =+DAY(H79) -> 0 | N79: =+IF(L79<10,_xlfn.CONCAT("0",L79),L79) -> 01 | O79: =+IF(M79<10,_xlfn.CONCAT("0",M79),M79) -> 00
J80: =+IF(I80<10,_xlfn.CONCAT("0",I80),I80) -> 0 | K80: =+YEAR(H80)-2000 -> -100 | L80: =+MONTH(H80) -> 1 | M80: =+DAY(H80) -> 0 | N80: =+IF(L80<10,_xlfn.CONCAT("0",L80),L80) -> 01 | O80: =+IF(M80<10,_xlfn.CONCAT("0",M80),M80) -> 00
J81: =+IF(I81<10,_xlfn.CONCAT("0",I81),I81) -> 0 | K81: =+YEAR(H81)-2000 -> -100 | L81: =+MONTH(H81) -> 1 | M81: =+DAY(H81) -> 0 | N81: =+IF(L81<10,_xlfn.CONCAT("0",L81),L81) -> 01 | O81: =+IF(M81<10,_xlfn.CONCAT("0",M81),M81) -> 00
J82: =+IF(I82<10,_xlfn.CONCAT("0",I82),I82) -> 0 | K82: =+YEAR(H82)-2000 -> -100 | L82: =+MONTH(H82) -> 1 | M82: =+DAY(H82) -> 0 | N82: =+IF(L82<10,_xlfn.CONCAT("0",L82),L82) -> 01 | O82: =+IF(M82<10,_xlfn.CONCAT("0",M82),M82) -> 00
... J158: =+IF(I158<10,_xlfn.CONCAT("0",I158),I158) -> 0 | K158: =+YEAR(H158)-2000 -> -100 | L158: =+MONTH(H158) -> 1 | M158: =+DAY(H158) -> 0 | N158: =+IF(L158<10,_xlfn.CONCAT("0",L158),L158) -> 01 | O158: =+IF(M158<10,_xlfn.CONCAT("0",M158),M158) -> 00
J159: =+IF(I159<10,_xlfn.CONCAT("0",I159),I159) -> 0 | K159: =+YEAR(H159)-2000 -> -100 | L159: =+MONTH(H159) -> 1 | M159: =+DAY(H159) -> 0 | N159: =+IF(L159<10,_xlfn.CONCAT("0",L159),L159) -> 01 | O159: =+IF(M159<10,_xlfn.CONCAT("0",M159),M159) -> 00 | S159: =IFERROR(P159/R159,"")
J160: =+IF(I160<10,_xlfn.CONCAT("0",I160),I160) -> 0 | K160: =+YEAR(H160)-2000 -> -100 | L160: =+MONTH(H160) -> 1 | M160: =+DAY(H160) -> 0 | N160: =+IF(L160<10,_xlfn.CONCAT("0",L160),L160) -> 01 | O160: =+IF(M160<10,_xlfn.CONCAT("0",M160),M160) -> 00
J161: =+IF(I161<10,_xlfn.CONCAT("0",I161),I161) -> 0 | K161: =+YEAR(H161)-2000 -> -100 | L161: =+MONTH(H161) -> 1 | M161: =+DAY(H161) -> 0 | N161: =+IF(L161<10,_xlfn.CONCAT("0",L161),L161) -> 01 | O161: =+IF(M161<10,_xlfn.CONCAT("0",M161),M161) -> 00
J162: =+IF(I162<10,_xlfn.CONCAT("0",I162),I162) -> 0 | K162: =+YEAR(H162)-2000 -> -100 | L162: =+MONTH(H162) -> 1 | M162: =+DAY(H162) -> 0 | N162: =+IF(L162<10,_xlfn.CONCAT("0",L162),L162) -> 01 | O162: =+IF(M162<10,_xlfn.CONCAT("0",M162),M162) -> 00
J163: =+IF(I163<10,_xlfn.CONCAT("0",I163),I163) -> 0 | K163: =+YEAR(H163)-2000 -> -100 | L163: =+MONTH(H163) -> 1 | M163: =+DAY(H163) -> 0 | N163: =+IF(L163<10,_xlfn.CONCAT("0",L163),L163) -> 01 | O163: =+IF(M163<10,_xlfn.CONCAT("0",M163),M163) -> 00
J164: =+IF(I164<10,_xlfn.CONCAT("0",I164),I164) -> 0 | K164: =+YEAR(H164)-2000 -> -100 | L164: =+MONTH(H164) -> 1 | M164: =+DAY(H164) -> 0 | N164: =+IF(L164<10,_xlfn.CONCAT("0",L164),L164) -> 01 | O164: =+IF(M164<10,_xlfn.CONCAT("0",M164),M164) -> 00
J165: =+IF(I165<10,_xlfn.CONCAT("0",I165),I165) -> 0 | K165: =+YEAR(H165)-2000 -> -100 | L165: =+MONTH(H165) -> 1 | M165: =+DAY(H165) -> 0 | N165: =+IF(L165<10,_xlfn.CONCAT("0",L165),L165) -> 01 | O165: =+IF(M165<10,_xlfn.CONCAT("0",M165),M165) -> 00
J166: =+IF(I166<10,_xlfn.CONCAT("0",I166),I166) -> 0 | K166: =+YEAR(H166)-2000 -> -100 | L166: =+MONTH(H166) -> 1 | M166: =+DAY(H166) -> 0 | N166: =+IF(L166<10,_xlfn.CONCAT("0",L166),L166) -> 01 | O166: =+IF(M166<10,_xlfn.CONCAT("0",M166),M166) -> 00
J167: =+IF(I167<10,_xlfn.CONCAT("0",I167),I167) -> 0 | K167: =+YEAR(H167)-2000 -> -100 | L167: =+MONTH(H167) -> 1 | M167: =+DAY(H167) -> 0 | N167: =+IF(L167<10,_xlfn.CONCAT("0",L167),L167) -> 01 | O167: =+IF(M167<10,_xlfn.CONCAT("0",M167),M167) -> 00
J168: =+IF(I168<10,_xlfn.CONCAT("0",I168),I168) -> 0 | K168: =+YEAR(H168)-2000 -> -100 | L168: =+MONTH(H168) -> 1 | M168: =+DAY(H168) -> 0 | N168: =+IF(L168<10,_xlfn.CONCAT("0",L168),L168) -> 01 | O168: =+IF(M168<10,_xlfn.CONCAT("0",M168),M168) -> 00
J169: =+IF(I169<10,_xlfn.CONCAT("0",I169),I169) -> 0 | K169: =+YEAR(H169)-2000 -> -100 | L169: =+MONTH(H169) -> 1 | M169: =+DAY(H169) -> 0 | N169: =+IF(L169<10,_xlfn.CONCAT("0",L169),L169) -> 01 | O169: =+IF(M169<10,_xlfn.CONCAT("0",M169),M169) -> 00
J170: =+IF(I170<10,_xlfn.CONCAT("0",I170),I170) -> 0 | K170: =+YEAR(H170)-2000 -> -100 | L170: =+MONTH(H170) -> 1 | M170: =+DAY(H170) -> 0 | N170: =+IF(L170<10,_xlfn.CONCAT("0",L170),L170) -> 01 | O170: =+IF(M170<10,_xlfn.CONCAT("0",M170),M170) -> 00
J171: =+IF(I171<10,_xlfn.CONCAT("0",I171),I171) -> 0 | K171: =+YEAR(H171)-2000 -> -100 | L171: =+MONTH(H171) -> 1 | M171: =+DAY(H171) -> 0 | N171: =+IF(L171<10,_xlfn.CONCAT("0",L171),L171) -> 01 | O171: =+IF(M171<10,_xlfn.CONCAT("0",M171),M171) -> 00
... J233: =+IF(I233<10,_xlfn.CONCAT("0",I233),I233) -> 0 | K233: =+YEAR(H233)-2000 -> -100 | L233: =+MONTH(H233) -> 1 | M233: =+DAY(H233) -> 0 | N233: =+IF(L233<10,_xlfn.CONCAT("0",L233),L233) -> 01 | O233: =+IF(M233<10,_xlfn.CONCAT("0",M233),M233) -> 00
K234: =+YEAR(H234)-2000 -> -100 | L234: =+MONTH(H234) -> 1 | M234: =+DAY(H234) -> 0 | N234: =+IF(L234<10,_xlfn.CONCAT("0",L234),L234) -> 01 | O234: =+IF(M234<10,_xlfn.CONCAT("0",M234),M234) -> 00
J235: =+IF(I235<10,_xlfn.CONCAT("0",I235),I235) -> 0 | K235: =+YEAR(H235)-2000 -> -100 | L235: =+MONTH(H235) -> 1 | M235: =+DAY(H235) -> 0 | N235: =+IF(L235<10,_xlfn.CONCAT("0",L235),L235) -> 01 | O235: =+IF(M235<10,_xlfn.CONCAT("0",M235),M235) -> 00
J236: =+IF(I236<10,_xlfn.CONCAT("0",I236),I236) -> 0 | K236: =+YEAR(H236)-2000 -> -100 | L236: =+MONTH(H236) -> 1 | M236: =+DAY(H236) -> 0 | N236: =+IF(L236<10,_xlfn.CONCAT("0",L236),L236) -> 01 | O236: =+IF(M236<10,_xlfn.CONCAT("0",M236),M236) -> 00
J237: =+IF(I237<10,_xlfn.CONCAT("0",I237),I237) -> 0 | K237: =+YEAR(H237)-2000 -> -100 | L237: =+MONTH(H237) -> 1 | M237: =+DAY(H237) -> 0 | N237: =+IF(L237<10,_xlfn.CONCAT("0",L237),L237) -> 01 | O237: =+IF(M237<10,_xlfn.CONCAT("0",M237),M237) -> 00
J238: =+IF(I238<10,_xlfn.CONCAT("0",I238),I238) -> 0 | K238: =+YEAR(H238)-2000 -> -100 | L238: =+MONTH(H238) -> 1 | M238: =+DAY(H238) -> 0 | N238: =+IF(L238<10,_xlfn.CONCAT("0",L238),L238) -> 01 | O238: =+IF(M238<10,_xlfn.CONCAT("0",M238),M238) -> 00
J239: =+IF(I239<10,_xlfn.CONCAT("0",I239),I239) -> 0 | K239: =+YEAR(H239)-2000 -> -100 | L239: =+MONTH(H239) -> 1 | M239: =+DAY(H239) -> 0 | N239: =+IF(L239<10,_xlfn.CONCAT("0",L239),L239) -> 01 | O239: =+IF(M239<10,_xlfn.CONCAT("0",M239),M239) -> 00
J240: =+IF(I240<10,_xlfn.CONCAT("0",I240),I240) -> 0 | K240: =+YEAR(H240)-2000 -> -100 | L240: =+MONTH(H240) -> 1 | M240: =+DAY(H240) -> 0 | N240: =+IF(L240<10,_xlfn.CONCAT("0",L240),L240) -> 01 | O240: =+IF(M240<10,_xlfn.CONCAT("0",M240),M240) -> 00
J241: =+IF(I241<10,_xlfn.CONCAT("0",I241),I241) -> 0 | K241: =+YEAR(H241)-2000 -> -100 | L241: =+MONTH(H241) -> 1 | M241: =+DAY(H241) -> 0 | N241: =+IF(L241<10,_xlfn.CONCAT("0",L241),L241) -> 01 | O241: =+IF(M241<10,_xlfn.CONCAT("0",M241),M241) -> 00
J242: =+IF(I242<10,_xlfn.CONCAT("0",I242),I242) -> 0 | K242: =+YEAR(H242)-2000 -> -100 | L242: =+MONTH(H242) -> 1 | M242: =+DAY(H242) -> 0 | N242: =+IF(L242<10,_xlfn.CONCAT("0",L242),L242) -> 01 | O242: =+IF(M242<10,_xlfn.CONCAT("0",M242),M242) -> 00
J243: =+IF(I243<10,_xlfn.CONCAT("0",I243),I243) -> 0 | K243: =+YEAR(H243)-2000 -> -100 | L243: =+MONTH(H243) -> 1 | M243: =+DAY(H243) -> 0 | N243: =+IF(L243<10,_xlfn.CONCAT("0",L243),L243) -> 01 | O243: =+IF(M243<10,_xlfn.CONCAT("0",M243),M243) -> 00
J244: =+IF(I244<10,_xlfn.CONCAT("0",I244),I244) -> 0 | K244: =+YEAR(H244)-2000 -> -100 | L244: =+MONTH(H244) -> 1 | M244: =+DAY(H244) -> 0 | N244: =+IF(L244<10,_xlfn.CONCAT("0",L244),L244) -> 01 | O244: =+IF(M244<10,_xlfn.CONCAT("0",M244),M244) -> 00
J245: =+IF(I245<10,_xlfn.CONCAT("0",I245),I245) -> 0 | K245: =+YEAR(H245)-2000 -> -100 | L245: =+MONTH(H245) -> 1 | M245: =+DAY(H245) -> 0 | N245: =+IF(L245<10,_xlfn.CONCAT("0",L245),L245) -> 01 | O245: =+IF(M245<10,_xlfn.CONCAT("0",M245),M245) -> 00
J246: =+IF(I246<10,_xlfn.CONCAT("0",I246),I246) -> 0 | K246: =+YEAR(H246)-2000 -> -100 | L246: =+MONTH(H246) -> 1 | M246: =+DAY(H246) -> 0 | N246: =+IF(L246<10,_xlfn.CONCAT("0",L246),L246) -> 01 | O246: =+IF(M246<10,_xlfn.CONCAT("0",M246),M246) -> 00
... J263: =+IF(I263<10,_xlfn.CONCAT("0",I263),I263) -> 0 | K263: =+YEAR(H263)-2000 -> -100 | L263: =+MONTH(H263) -> 1 | M263: =+DAY(H263) -> 0 | N263: =+IF(L263<10,_xlfn.CONCAT("0",L263),L263) -> 01 | O263: =+IF(M263<10,_xlfn.CONCAT("0",M263),M263) -> 00
J264: =+IF(I264<10,_xlfn.CONCAT("0",I264),I264) -> 0 | K264: =+YEAR(H264)-2000 -> -100 | L264: =+MONTH(H264) -> 1 | M264: =+DAY(H264) -> 0 | N264: =+IF(L264<10,_xlfn.CONCAT("0",L264),L264) -> 01 | O264: =+IF(M264<10,_xlfn.CONCAT("0",M264),M264) -> 00 | R264: 494 | S264: =+P264/R264 -> 0
J265: =+IF(I265<10,_xlfn.CONCAT("0",I265),I265) -> 0 | K265: =+YEAR(H265)-2000 -> -100 | L265: =+MONTH(H265) -> 1 | M265: =+DAY(H265) -> 0 | N265: =+IF(L265<10,_xlfn.CONCAT("0",L265),L265) -> 01 | O265: =+IF(M265<10,_xlfn.CONCAT("0",M265),M265) -> 00 | R265: 494 | S265: =+P265/R265 -> 0
J266: =+IF(I266<10,_xlfn.CONCAT("0",I266),I266) -> 0 | K266: =+YEAR(H266)-2000 -> -100 | L266: =+MONTH(H266) -> 1 | M266: =+DAY(H266) -> 0 | N266: =+IF(L266<10,_xlfn.CONCAT("0",L266),L266) -> 01 | O266: =+IF(M266<10,_xlfn.CONCAT("0",M266),M266) -> 00 | R266: 494 | S266: =+P266/R266 -> 0
J267: =+IF(I267<10,_xlfn.CONCAT("0",I267),I267) -> 0 | K267: =+YEAR(H267)-2000 -> -100 | L267: =+MONTH(H267) -> 1 | M267: =+DAY(H267) -> 0 | N267: =+IF(L267<10,_xlfn.CONCAT("0",L267),L267) -> 01 | O267: =+IF(M267<10,_xlfn.CONCAT("0",M267),M267) -> 00
J268: =+IF(I268<10,_xlfn.CONCAT("0",I268),I268) -> 0 | K268: =+YEAR(H268)-2000 -> -100 | L268: =+MONTH(H268) -> 1 | M268: =+DAY(H268) -> 0 | N268: =+IF(L268<10,_xlfn.CONCAT("0",L268),L268) -> 01 | O268: =+IF(M268<10,_xlfn.CONCAT("0",M268),M268) -> 00
J269: =+IF(I269<10,_xlfn.CONCAT("0",I269),I269) -> 0 | K269: =+YEAR(H269)-2000 -> -100 | L269: =+MONTH(H269) -> 1 | M269: =+DAY(H269) -> 0 | N269: =+IF(L269<10,_xlfn.CONCAT("0",L269),L269) -> 01 | O269: =+IF(M269<10,_xlfn.CONCAT("0",M269),M269) -> 00
J270: =+IF(I270<10,_xlfn.CONCAT("0",I270),I270) -> 0 | K270: =+YEAR(H270)-2000 -> -100 | L270: =+MONTH(H270) -> 1 | M270: =+DAY(H270) -> 0 | N270: =+IF(L270<10,_xlfn.CONCAT("0",L270),L270) -> 01 | O270: =+IF(M270<10,_xlfn.CONCAT("0",M270),M270) -> 00
J271: =+IF(I271<10,_xlfn.CONCAT("0",I271),I271) -> 0 | K271: =+YEAR(H271)-2000 -> -100 | L271: =+MONTH(H271) -> 1 | M271: =+DAY(H271) -> 0 | N271: =+IF(L271<10,_xlfn.CONCAT("0",L271),L271) -> 01 | O271: =+IF(M271<10,_xlfn.CONCAT("0",M271),M271) -> 00
J275: =+IF(I275<10,_xlfn.CONCAT("0",I275),I275) -> 0 | K275: =+YEAR(H275)-2000 -> -100 | L275: =+MONTH(H275) -> 1 | M275: =+DAY(H275) -> 0 | N275: =+IF(L275<10,_xlfn.CONCAT("0",L275),L275) -> 01 | O275: =+IF(M275<10,_xlfn.CONCAT("0",M275),M275) -> 00
J276: =+IF(I276<10,_xlfn.CONCAT("0",I276),I276) -> 0 | K276: =+YEAR(H276)-2000 -> -100 | L276: =+MONTH(H276) -> 1 | M276: =+DAY(H276) -> 0 | N276: =+IF(L276<10,_xlfn.CONCAT("0",L276),L276) -> 01 | O276: =+IF(M276<10,_xlfn.CONCAT("0",M276),M276) -> 00
J277: =+IF(I277<10,_xlfn.CONCAT("0",I277),I277) -> 0 | K277: =+YEAR(H277)-2000 -> -100 | L277: =+MONTH(H277) -> 1 | M277: =+DAY(H277) -> 0 | N277: =+IF(L277<10,_xlfn.CONCAT("0",L277),L277) -> 01 | O277: =+IF(M277<10,_xlfn.CONCAT("0",M277),M277) -> 00
J278: =+IF(I278<10,_xlfn.CONCAT("0",I278),I278) -> 0 | K278: =+YEAR(H278)-2000 -> -100 | L278: =+MONTH(H278) -> 1 | M278: =+DAY(H278) -> 0 | N278: =+IF(L278<10,_xlfn.CONCAT("0",L278),L278) -> 01 | O278: =+IF(M278<10,_xlfn.CONCAT("0",M278),M278) -> 00
J279: =+IF(I279<10,_xlfn.CONCAT("0",I279),I279) -> 0 | K279: =+YEAR(H279)-2000 -> -100 | L279: =+MONTH(H279) -> 1 | M279: =+DAY(H279) -> 0 | N279: =+IF(L279<10,_xlfn.CONCAT("0",L279),L279) -> 01 | O279: =+IF(M279<10,_xlfn.CONCAT("0",M279),M279) -> 00
J280: =+IF(I280<10,_xlfn.CONCAT("0",I280),I280) -> 0 | K280: =+YEAR(H280)-2000 -> -100 | L280: =+MONTH(H280) -> 1 | M280: =+DAY(H280) -> 0 | N280: =+IF(L280<10,_xlfn.CONCAT("0",L280),L280) -> 01 | O280: =+IF(M280<10,_xlfn.CONCAT("0",M280),M280) -> 00
J281: =+IF(I281<10,_xlfn.CONCAT("0",I281),I281) -> 0 | K281: =+YEAR(H281)-2000 -> -100 | L281: =+MONTH(H281) -> 1 | M281: =+DAY(H281) -> 0 | N281: =+IF(L281<10,_xlfn.CONCAT("0",L281),L281) -> 01 | O281: =+IF(M281<10,_xlfn.CONCAT("0",M281),M281) -> 00
... J283: =+IF(I283<10,_xlfn.CONCAT("0",I283),I283) -> 0 | K283: =+YEAR(H283)-2000 -> -100 | L283: =+MONTH(H283) -> 1 | M283: =+DAY(H283) -> 0 | N283: =+IF(L283<10,_xlfn.CONCAT("0",L283),L283) -> 01 | O283: =+IF(M283<10,_xlfn.CONCAT("0",M283),M283) -> 00
A284: 277 | B284: =IF(G284="-",0,IF(G283=G284,1,0)) -> 0 | C284: =+IF(G284="-",0,IF(I284=I283+1,0,(IF(I284=1,0,1)))) -> 1 | D284: =+IF(AND(P284="",Q284=""),1,0) -> 0 | E284: =IF(U284="",1,0) -> 1 | F284: =IF(V284="",1,0) -> 0 | G284: =IF(H284=0,"-",_xlfn.CONCAT(K284,N284,O284,J284)) -> 24042510 | H284: 45407 | I284: 10 | J284: =+IF(I284<10,_xlfn.CONCAT("0",I284),I284) -> 10 | K284: =+YEAR(H284)-2000 -> 24 | L284: =+MONTH(H284) -> 4 | M284: =+DAY(H284) -> 25 | N284: =+IF(L284<10,_xlfn.CONCAT("0",L284),L284) -> 04 | O284: =+IF(M284<10,_xlfn.CONCAT("0",M284),M284) -> 25 | P284: 1705727.9 | T284: B31 cot #56810 colono | V284: PGE B31
J285: =+IF(I285<10,_xlfn.CONCAT("0",I285),I285) -> 0 | K285: =+YEAR(H285)-2000 -> -100 | L285: =+MONTH(H285) -> 1 | M285: =+DAY(H285) -> 0 | N285: =+IF(L285<10,_xlfn.CONCAT("0",L285),L285) -> 01 | O285: =+IF(M285<10,_xlfn.CONCAT("0",M285),M285) -> 00
J286: =+IF(I286<10,_xlfn.CONCAT("0",I286),I286) -> 0 | K286: =+YEAR(H286)-2000 -> -100 | L286: =+MONTH(H286) -> 1 | M286: =+DAY(H286) -> 0 | N286: =+IF(L286<10,_xlfn.CONCAT("0",L286),L286) -> 01 | O286: =+IF(M286<10,_xlfn.CONCAT("0",M286),M286) -> 00
J287: =+IF(I287<10,_xlfn.CONCAT("0",I287),I287) -> 0 | K287: =+YEAR(H287)-2000 -> -100 | L287: =+MONTH(H287) -> 1 | M287: =+DAY(H287) -> 0 | N287: =+IF(L287<10,_xlfn.CONCAT("0",L287),L287) -> 01 | O287: =+IF(M287<10,_xlfn.CONCAT("0",M287),M287) -> 00
J288: =+IF(I288<10,_xlfn.CONCAT("0",I288),I288) -> 0 | K288: =+YEAR(H288)-2000 -> -100 | L288: =+MONTH(H288) -> 1 | M288: =+DAY(H288) -> 0 | N288: =+IF(L288<10,_xlfn.CONCAT("0",L288),L288) -> 01 | O288: =+IF(M288<10,_xlfn.CONCAT("0",M288),M288) -> 00
J289: =+IF(I289<10,_xlfn.CONCAT("0",I289),I289) -> 0 | K289: =+YEAR(H289)-2000 -> -100 | L289: =+MONTH(H289) -> 1 | M289: =+DAY(H289) -> 0 | N289: =+IF(L289<10,_xlfn.CONCAT("0",L289),L289) -> 01 | O289: =+IF(M289<10,_xlfn.CONCAT("0",M289),M289) -> 00
J290: =+IF(I290<10,_xlfn.CONCAT("0",I290),I290) -> 0 | K290: =+YEAR(H290)-2000 -> -100 | L290: =+MONTH(H290) -> 1 | M290: =+DAY(H290) -> 0 | N290: =+IF(L290<10,_xlfn.CONCAT("0",L290),L290) -> 01 | O290: =+IF(M290<10,_xlfn.CONCAT("0",M290),M290) -> 00
J291: =+IF(I291<10,_xlfn.CONCAT("0",I291),I291) -> 0 | K291: =+YEAR(H291)-2000 -> -100 | L291: =+MONTH(H291) -> 1 | M291: =+DAY(H291) -> 0 | N291: =+IF(L291<10,_xlfn.CONCAT("0",L291),L291) -> 01 | O291: =+IF(M291<10,_xlfn.CONCAT("0",M291),M291) -> 00
J292: =+IF(I292<10,_xlfn.CONCAT("0",I292),I292) -> 0 | K292: =+YEAR(H292)-2000 -> -100 | L292: =+MONTH(H292) -> 1 | M292: =+DAY(H292) -> 0 | N292: =+IF(L292<10,_xlfn.CONCAT("0",L292),L292) -> 01 | O292: =+IF(M292<10,_xlfn.CONCAT("0",M292),M292) -> 00
J293: =+IF(I293<10,_xlfn.CONCAT("0",I293),I293) -> 0 | K293: =+YEAR(H293)-2000 -> -100 | L293: =+MONTH(H293) -> 1 | M293: =+DAY(H293) -> 0 | N293: =+IF(L293<10,_xlfn.CONCAT("0",L293),L293) -> 01 | O293: =+IF(M293<10,_xlfn.CONCAT("0",M293),M293) -> 00
J294: =+IF(I294<10,_xlfn.CONCAT("0",I294),I294) -> 0 | K294: =+YEAR(H294)-2000 -> -100 | L294: =+MONTH(H294) -> 1 | M294: =+DAY(H294) -> 0 | N294: =+IF(L294<10,_xlfn.CONCAT("0",L294),L294) -> 01 | O294: =+IF(M294<10,_xlfn.CONCAT("0",M294),M294) -> 00
J295: =+IF(I295<10,_xlfn.CONCAT("0",I295),I295) -> 0 | K295: =+YEAR(H295)-2000 -> -100 | L295: =+MONTH(H295) -> 1 | M295: =+DAY(H295) -> 0 | N295: =+IF(L295<10,_xlfn.CONCAT("0",L295),L295) -> 01 | O295: =+IF(M295<10,_xlfn.CONCAT("0",M295),M295) -> 00
J296: =+IF(I296<10,_xlfn.CONCAT("0",I296),I296) -> 0 | K296: =+YEAR(H296)-2000 -> -100 | L296: =+MONTH(H296) -> 1 | M296: =+DAY(H296) -> 0 | N296: =+IF(L296<10,_xlfn.CONCAT("0",L296),L296) -> 01 | O296: =+IF(M296<10,_xlfn.CONCAT("0",M296),M296) -> 00
... J308: =+IF(I308<10,_xlfn.CONCAT("0",I308),I308) -> 0 | K308: =+YEAR(H308)-2000 -> -100 | L308: =+MONTH(H308) -> 1 | M308: =+DAY(H308) -> 0 | N308: =+IF(L308<10,_xlfn.CONCAT("0",L308),L308) -> 01 | O308: =+IF(M308<10,_xlfn.CONCAT("0",M308),M308) -> 00
A309: 302 | B309: =IF(G309="-",0,IF(G308=G309,1,0)) -> 0 | C309: =+IF(G309="-",0,IF(I309=I308+1,0,(IF(I309=1,0,1)))) -> 1 | D309: =+IF(AND(P309="",Q309=""),1,0) -> 0 | E309: =IF(U309="",1,0) -> 0 | F309: =IF(V309="",1,0) -> 0 | G309: =IF(H309=0,"-",_xlfn.CONCAT(K309,N309,O309,J309)) -> 24042609 | H309: 45408 | I309: 9 | J309: =+IF(I309<10,_xlfn.CONCAT("0",I309),I309) -> 09 | K309: =+YEAR(H309)-2000 -> 24 | L309: =+MONTH(H309) -> 4 | M309: =+DAY(H309) -> 26 | N309: =+IF(L309<10,_xlfn.CONCAT("0",L309),L309) -> 04 | O309: =+IF(M309<10,_xlfn.CONCAT("0",M309),M309) -> 26 | P309: 1705727.9 | T309: Almacenes El Colono - Huacas cot #56810 | U309: BacC | V309: PGE B31
J310: =+IF(I310<10,_xlfn.CONCAT("0",I310),I310) -> 0 | K310: =+YEAR(H310)-2000 -> -100 | L310: =+MONTH(H310) -> 1 | M310: =+DAY(H310) -> 0 | N310: =+IF(L310<10,_xlfn.CONCAT("0",L310),L310) -> 01 | O310: =+IF(M310<10,_xlfn.CONCAT("0",M310),M310) -> 00
...

Sheet 2025 b31
G1: id iguales? | H1: =SUM(B:B) -> 2
G2: id consecutivos? | H2: =SUM(C:C) -> #VALUE!
G3: sin precio | H3: =SUM(D:D) -> 60
G4: sin formade pago | H4: =SUM(E:E) -> 152
G5: sin centro de costo | H5: =SUM(F:F) -> 60
A7: N | B7: id iguales? | C7: id consecutivos? | D7: sin precio | E7: sin formade pago | F7: sin centro de costo | G7: identificador | H7: Fecha | I7: Diario | J7: Column2 | K7: Column3 | L7: Column4 | M7: Column5 | N7: Column6 | O7: Column7 | P7: Colones | Q7: Dolares | R7: Tipo Cambio | S7: Precio en $ | T7: Descripcion | U7: forma de pago | V7: CC | W7: Medio | X7: FD | Y7: Observaciones
A8: 7 | B8: =IF(G8="-",0,IF(G7=G8,1,0)) -> 0 | C8: =+IF(G8="-",0,IF(I8=I7+1,0,(IF(I8=1,0,1)))) -> #VALUE! | D8: =+IF(AND(P8="",Q8=""),1,0) -> 0 | E8: =IF(U8="",1,0) -> 0 | F8: =IF(V8="",1,0) -> 0 | G8: =IF(H8=0,"-",_xlfn.CONCAT(K8,N8,O8,J8)) -> 25010201 | H8: 45659 | I8: 1 | J8: =+IF(I8<10,_xlfn.CONCAT("0",I8),I8) -> 01 | K8: =+YEAR(H8)-2000 -> 25 | L8: =+MONTH(H8) -> 1 | M8: =+DAY(H8) -> 2 | N8: =+IF(L8<10,_xlfn.CONCAT("0",L8),L8) -> 01 | O8: =+IF(M8<10,_xlfn.CONCAT("0",M8),M8) -> 02 | P8: 44592.69 | T8: Almacenes El Colono SA - Huacas - Trampa de Grasa | U8: Grillo | V8: PGE B31 | W8: Terceros | X8: ✓
A9: 8 | B9: =IF(G9="-",0,IF(G8=G9,1,0)) -> 0 | C9: =+IF(G9="-",0,IF(I9=I8+1,0,(IF(I9=1,0,1)))) -> 0 | D9: =+IF(AND(P9="",Q9=""),1,0) -> 0 | E9: =IF(U9="",1,0) -> 0 | F9: =IF(V9="",1,0) -> 0 | G9: =IF(H9=0,"-",_xlfn.CONCAT(K9,N9,O9,J9)) -> 25010202 | H9: 45659 | I9: 2 | J9: =+IF(I9<10,_xlfn.CONCAT("0",I9),I9) -> 02 | K9: =+YEAR(H9)-2000 -> 25 | L9: =+MONTH(H9) -> 1 | M9: =+DAY(H9) -> 2 | N9: =+IF(L9<10,_xlfn.CONCAT("0",L9),L9) -> 01 | O9: =+IF(M9<10,_xlfn.CONCAT("0",M9),M9) -> 02 | P9: 16549.98 | T9: Almacenes El Colono SA - Huacas - Cinta Led | U9: Grillo | V9: PGE B31 | W9: Terceros | X9: ✓
A10: 9 | B10: =IF(G10="-",0,IF(G9=G10,1,0)) -> 0 | C10: =+IF(G10="-",0,IF(I10=I9+1,0,(IF(I10=1,0,1)))) -> 0 | D10: =+IF(AND(P10="",Q10=""),1,0) -> 0 | E10: =IF(U10="",1,0) -> 0 | F10: =IF(V10="",1,0) -> 0 | G10: =IF(H10=0,"-",_xlfn.CONCAT(K10,N10,O10,J10)) -> 25010203 | H10: 45659 | I10: 3 | J10: =+IF(I10<10,_xlfn.CONCAT("0",I10),I10) -> 03 | K10: =+YEAR(H10)-2000 -> 25 | L10: =+MONTH(H10) -> 1 | M10: =+DAY(H10) -> 2 | N10: =+IF(L10<10,_xlfn.CONCAT("0",L10),L10) -> 01 | O10: =+IF(M10<10,_xlfn.CONCAT("0",M10),M10) -> 02 | P10: 5304.14 | T10: MAFERCO S.A. - Ref 267512 - Broca | U10: Grillo | V10: PGE C30 | W10: Terceros | X10: ✓
J11: =+IF(I11<10,_xlfn.CONCAT("0",I11),I11) -> 0 | K11: =+YEAR(H11)-2000 -> -100 | L11: =+MONTH(H11) -> 1 | M11: =+DAY(H11) -> 0 | N11: =+IF(L11<10,_xlfn.CONCAT("0",L11),L11) -> 01 | O11: =+IF(M11<10,_xlfn.CONCAT("0",M11),M11) -> 00
A12: 1 | D12: =+IF(AND(P12="",Q12=""),1,0) -> 0 | E12: =IF(U12="",1,0) -> 0 | F12: =IF(V12="",1,0) -> 0 | G12: =IF(H12=0,"-",_xlfn.CONCAT(K12,N12,O12,J12)) -> 25010301 | H12: 45660 | I12: 1 | J12: =+IF(I12<10,_xlfn.CONCAT("0",I12),I12) -> 01 | K12: =+YEAR(H12)-2000 -> 25 | L12: =+MONTH(H12) -> 1 | M12: =+DAY(H12) -> 3 | N12: =+IF(L12<10,_xlfn.CONCAT("0",L12),L12) -> 01 | O12: =+IF(M12<10,_xlfn.CONCAT("0",M12),M12) -> 03 | P12: 200000 | T12: Caja Chica B31 - Exner Grillo | U12: BacD | V12: PGE B31 | W12: Transferencia | X12: ✓ | Y12: 1046
J13: =+IF(I13<10,_xlfn.CONCAT("0",I13),I13) -> 0 | K13: =+YEAR(H13)-2000 -> -100 | L13: =+MONTH(H13) -> 1 | M13: =+DAY(H13) -> 0 | N13: =+IF(L13<10,_xlfn.CONCAT("0",L13),L13) -> 01 | O13: =+IF(M13<10,_xlfn.CONCAT("0",M13),M13) -> 00
J14: =+IF(I14<10,_xlfn.CONCAT("0",I14),I14) -> 0 | K14: =+YEAR(H14)-2000 -> -100 | L14: =+MONTH(H14) -> 1 | M14: =+DAY(H14) -> 0 | N14: =+IF(L14<10,_xlfn.CONCAT("0",L14),L14) -> 01 | O14: =+IF(M14<10,_xlfn.CONCAT("0",M14),M14) -> 00
A15: 4 | B15: =IF(G15="-",0,IF(G14=G15,1,0)) -> 0 | C15: =+IF(G15="-",0,IF(I15=I14+1,0,(IF(I15=1,0,1)))) -> 1 | D15: =+IF(AND(P15="",Q15=""),1,0) -> 0 | E15: =IF(U15="",1,0) -> 0 | F15: =IF(V15="",1,0) -> 0 | G15: =IF(H15=0,"-",_xlfn.CONCAT(K15,N15,O15,J15)) -> 25010304 | H15: 45660 | I15: 4 | J15: =+IF(I15<10,_xlfn.CONCAT("0",I15),I15) -> 04 | K15: =+YEAR(H15)-2000 -> 25 | L15: =+MONTH(H15) -> 1 | M15: =+DAY(H15) -> 3 | N15: =+IF(L15<10,_xlfn.CONCAT("0",L15),L15) -> 01 | O15: =+IF(M15<10,_xlfn.CONCAT("0",M15),M15) -> 03 | P15: 54008.32 | T15: Coopeguanacaste RL - Electricidad Ref 206349 | U15: BacC | V15: PGE B31 | W15: Transferencia | Y15: 1046
A16: 10 | B16: =IF(G16="-",0,IF(G15=G16,1,0)) -> 0 | C16: =+IF(G16="-",0,IF(I16=I15+1,0,(IF(I16=1,0,1)))) -> 0 | D16: =+IF(AND(P16="",Q16=""),1,0) -> 0 | E16: =IF(U16="",1,0) -> 0 | F16: =IF(V16="",1,0) -> 0 | G16: =IF(H16=0,"-",_xlfn.CONCAT(K16,N16,O16,J16)) -> 25010305 | H16: 45660 | I16: 5 | J16: =+IF(I16<10,_xlfn.CONCAT("0",I16),I16) -> 05 | K16: =+YEAR(H16)-2000 -> 25 | L16: =+MONTH(H16) -> 1 | M16: =+DAY(H16) -> 3 | N16: =+IF(L16<10,_xlfn.CONCAT("0",L16),L16) -> 01 | O16: =+IF(M16<10,_xlfn.CONCAT("0",M16),M16) -> 03 | P16: 39892.55 | T16: MAFERCO S.A. - Ref 103391 - Piedra Quinta Blanca 2m3 | U16: Grillo | V16: PGE C30 | W16: Terceros | X16: ✓
J17: =+IF(I17<10,_xlfn.CONCAT("0",I17),I17) -> 0 | K17: =+YEAR(H17)-2000 -> -100 | L17: =+MONTH(H17) -> 1 | M17: =+DAY(H17) -> 0 | N17: =+IF(L17<10,_xlfn.CONCAT("0",L17),L17) -> 01 | O17: =+IF(M17<10,_xlfn.CONCAT("0",M17),M17) -> 00
A18: 15 | B18: =IF(G18="-",0,IF(G17=G18,1,0)) -> 0 | C18: =+IF(G18="-",0,IF(I18=I17+1,0,(IF(I18=1,0,1)))) -> 1 | D18: =+IF(AND(P18="",Q18=""),1,0) -> 0 | E18: =IF(U18="",1,0) -> 0 | F18: =IF(V18="",1,0) -> 0 | G18: =IF(H18=0,"-",_xlfn.CONCAT(K18,N18,O18,J18)) -> 25010307 | H18: 45660 | I18: 7 | J18: =+IF(I18<10,_xlfn.CONCAT("0",I18),I18) -> 07 | K18: =+YEAR(H18)-2000 -> 25 | L18: =+MONTH(H18) -> 1 | M18: =+DAY(H18) -> 3 | N18: =+IF(L18<10,_xlfn.CONCAT("0",L18),L18) -> 01 | O18: =+IF(M18<10,_xlfn.CONCAT("0",M18),M18) -> 03 | P18: 30000 | T18: Wagner Zepeda Bustos [8770-8682] - Transporte Quintilla | U18: Grillo | V18: PGE C30 | W18: SINPE Movil | X18: × | Y18: 8433
A19: 262 | B19: =IF(G19="-",0,IF(G18=G19,1,0)) -> 0 | C19: =+IF(G19="-",0,IF(I19=I18+1,0,(IF(I19=1,0,1)))) -> 0 | D19: =+IF(AND(P18="",Q19=""),1,0) -> 0 | E19: =IF(U19="",1,0) -> 0 | F19: =IF(V19="",1,0) -> 0 | G19: =IF(H19=0,"-",_xlfn.CONCAT(K19,N19,O19,J19)) -> 25010308 | H19: 45660 | I19: 8 | J19: =+IF(I19<10,_xlfn.CONCAT("0",I19),I19) -> 08 | K19: =+YEAR(H19)-2000 -> 25 | L19: =+MONTH(H19) -> 1 | M19: =+DAY(H19) -> 3 | N19: =+IF(L19<10,_xlfn.CONCAT("0",L19),L19) -> 01 | O19: =+IF(M19<10,_xlfn.CONCAT("0",M19),M19) -> 03 | P19: 10000 | T19: Combustible - SERVIMOVIL HUACAS S.A (Viaticos Grillo) | U19: Grillo | V19: PGE B31 | W19: Terceros | X19: ✓
J20: =+IF(I20<10,_xlfn.CONCAT("0",I20),I20) -> 0 | K20: =+YEAR(H20)-2000 -> -100 | L20: =+MONTH(H20) -> 1 | M20: =+DAY(H20) -> 0 | N20: =+IF(L20<10,_xlfn.CONCAT("0",L20),L20) -> 01 | O20: =+IF(M20<10,_xlfn.CONCAT("0",M20),M20) -> 00
J21: =+IF(I21<10,_xlfn.CONCAT("0",I21),I21) -> 0 | K21: =+YEAR(H21)-2000 -> -100 | L21: =+MONTH(H21) -> 1 | M21: =+DAY(H21) -> 0 | N21: =+IF(L21<10,_xlfn.CONCAT("0",L21),L21) -> 01 | O21: =+IF(M21<10,_xlfn.CONCAT("0",M21),M21) -> 00
A22: 17 | B22: =IF(G22="-",0,IF(G21=G22,1,0)) -> 0 | C22: =+IF(G22="-",0,IF(I22=I21+1,0,(IF(I22=1,0,1)))) -> 1 | D22: =+IF(AND(P22="",Q22=""),1,0) -> 0 | E22: =IF(U22="",1,0) -> 0 | F22: =IF(V22="",1,0) -> 0 | G22: =IF(H22=0,"-",_xlfn.CONCAT(K22,N22,O22,J22)) -> 25010502 | H22: 45662 | I22: 2 | J22: =+IF(I22<10,_xlfn.CONCAT("0",I22),I22) -> 02 | K22: =+YEAR(H22)-2000 -> 25 | L22: =+MONTH(H22) -> 1 | M22: =+DAY(H22) -> 5 | N22: =+IF(L22<10,_xlfn.CONCAT("0",L22),L22) -> 01 | O22: =+IF(M22<10,_xlfn.CONCAT("0",M22),M22) -> 05 | P22: 21200 | T22: B31 Planilla 31 diciembre al 4 enero - Geyvin Centeno | U22: BacC | V22: PGE B31 | W22: Transferencia | X22: × | Y22: *0081
A23: 18 | B23: =IF(G23="-",0,IF(G22=G23,1,0)) -> 0 | C23: =+IF(G23="-",0,IF(I23=I22+1,0,(IF(I23=1,0,1)))) -> 0 | D23: =+IF(AND(P23="",Q23=""),1,0) -> 0 | E23: =IF(U23="",1,0) -> 0 | F23: =IF(V23="",1,0) -> 0 | G23: =IF(H23=0,"-",_xlfn.CONCAT(K23,N23,O23,J23)) -> 25010503 | H23: 45662 | I23: 3 | J23: =+IF(I23<10,_xlfn.CONCAT("0",I23),I23) -> 03 | K23: =+YEAR(H23)-2000 -> 25 | L23: =+MONTH(H23) -> 1 | M23: =+DAY(H23) -> 5 | N23: =+IF(L23<10,_xlfn.CONCAT("0",L23),L23) -> 01 | O23: =+IF(M23<10,_xlfn.CONCAT("0",M23),M23) -> 05 | P23: 17600 | T23: B31 Planilla 31 diciembre al 4 enero - Eliceo García Espinosa | U23: BacC | V23: PGE B31 | W23: Transferencia | X23: × | Y23: *0081
A24: 19 | B24: =IF(G24="-",0,IF(G23=G24,1,0)) -> 0 | C24: =+IF(G24="-",0,IF(I24=I23+1,0,(IF(I24=1,0,1)))) -> 0 | D24: =+IF(AND(P24="",Q24=""),1,0) -> 0 | E24: =IF(U24="",1,0) -> 0 | F24: =IF(V24="",1,0) -> 0 | G24: =IF(H24=0,"-",_xlfn.CONCAT(K24,N24,O24,J24)) -> 25010504 | H24: 45662 | I24: 4 | J24: =+IF(I24<10,_xlfn.CONCAT("0",I24),I24) -> 04 | K24: =+YEAR(H24)-2000 -> 25 | L24: =+MONTH(H24) -> 1 | M24: =+DAY(H24) -> 5 | N24: =+IF(L24<10,_xlfn.CONCAT("0",L24),L24) -> 01 | O24: =+IF(M24<10,_xlfn.CONCAT("0",M24),M24) -> 05 | P24: 138000 | T24: B31 Planilla 31 diciembre al 4 enero - Omar Elias Castillo Castillo. DEPOSITA A MARTA PEREZ | U24: BacC | V24: PGE B31 | W24: Transferencia | X24: × | Y24: *0081
A25: 20 | B25: =IF(G25="-",0,IF(G24=G25,1,0)) -> 0 | C25: =+IF(G25="-",0,IF(I25=I24+1,0,(IF(I25=1,0,1)))) -> 0 | D25: =+IF(AND(P25="",Q25=""),1,0) -> 0 | E25: =IF(U25="",1,0) -> 0 | F25: =IF(V25="",1,0) -> 0 | G25: =IF(H25=0,"-",_xlfn.CONCAT(K25,N25,O25,J25)) -> 25010505 | H25: 45662 | I25: 5 | J25: =+IF(I25<10,_xlfn.CONCAT("0",I25),I25) -> 05 | K25: =+YEAR(H25)-2000 -> 25 | L25: =+MONTH(H25) -> 1 | M25: =+DAY(H25) -> 5 | N25: =+IF(L25<10,_xlfn.CONCAT("0",L25),L25) -> 01 | O25: =+IF(M25<10,_xlfn.CONCAT("0",M25),M25) -> 05 | P25: 17600 | T25: B31 Planilla 31 diciembre al 4 enero - Eliecer Leonardo Lacayo | U25: BacC | V25: PGE B31 | W25: Transferencia | X25: × | Y25: *0081
A26: 21 | B26: =IF(G26="-",0,IF(G25=G26,1,0)) -> 0 | C26: =+IF(G26="-",0,IF(I26=I25+1,0,(IF(I26=1,0,1)))) -> 0 | D26: =+IF(AND(P26="",Q26=""),1,0) -> 0 | E26: =IF(U26="",1,0) -> 0 | F26: =IF(V26="",1,0) -> 0 | G26: =IF(H26=0,"-",_xlfn.CONCAT(K26,N26,O26,J26)) -> 25010506 | H26: 45662 | I26: 6 | J26: =+IF(I26<10,_xlfn.CONCAT("0",I26),I26) -> 06 | K26: =+YEAR(H26)-2000 -> 25 | L26: =+MONTH(H26) -> 1 | M26: =+DAY(H26) -> 5 | N26: =+IF(L26<10,_xlfn.CONCAT("0",L26),L26) -> 01 | O26: =+IF(M26<10,_xlfn.CONCAT("0",M26),M26) -> 05 | P26: 17600 | T26: B31 Planilla 31 diciembre al 4 enero - Freddy Antonio Hernandez | U26: BacC | V26: PGE B31 | W26: Transferencia | X26: × | Y26: *0081
A27: 22 | B27: =IF(G27="-",0,IF(G26=G27,1,0)) -> 0 | C27: =+IF(G27="-",0,IF(I27=I26+1,0,(IF(I27=1,0,1)))) -> 0 | D27: =+IF(AND(P27="",Q27=""),1,0) -> 0 | E27: =IF(U27="",1,0) -> 0 | F27: =IF(V27="",1,0) -> 0 | G27: =IF(H27=0,"-",_xlfn.CONCAT(K27,N27,O27,J27)) -> 25010507 | H27: 45662 | I27: 7 | J27: =+IF(I27<10,_xlfn.CONCAT("0",I27),I27) -> 07 | K27: =+YEAR(H27)-2000 -> 25 | L27: =+MONTH(H27) -> 1 | M27: =+DAY(H27) -> 5 | N27: =+IF(L27<10,_xlfn.CONCAT("0",L27),L27) -> 01 | O27: =+IF(M27<10,_xlfn.CONCAT("0",M27),M27) -> 05 | P27: 21200 | T27: B31 Planilla 31 diciembre al 4 enero - Michael Medina Corea | U27: BacC | V27: PGE B31 | W27: Transferencia | X27: × | Y27: *0081
A28: 23 | B28: =IF(G28="-",0,IF(G27=G28,1,0)) -> 0 | C28: =+IF(G28="-",0,IF(I28=I27+1,0,(IF(I28=1,0,1)))) -> 0 | D28: =+IF(AND(P28="",Q28=""),1,0) -> 0 | E28: =IF(U28="",1,0) -> 0 | F28: =IF(V28="",1,0) -> 0 | G28: =IF(H28=0,"-",_xlfn.CONCAT(K28,N28,O28,J28)) -> 25010508 | H28: 45662 | I28: 8 | J28: =+IF(I28<10,_xlfn.CONCAT("0",I28),I28) -> 08 | K28: =+YEAR(H28)-2000 -> 25 | L28: =+MONTH(H28) -> 1 | M28: =+DAY(H28) -> 5 | N28: =+IF(L28<10,_xlfn.CONCAT("0",L28),L28) -> 01 | O28: =+IF(M28<10,_xlfn.CONCAT("0",M28),M28) -> 05 | P28: 150000 | T28: B31 4 enero EXNER GRILLO - Comida | U28: BacC | V28: PGE B31 | W28: Transferencia | Y28: s7
A29: 24 | B29: =IF(G29="-",0,IF(G28=G29,1,0)) -> 0 | C29: =+IF(G29="-",0,IF(I29=I28+1,0,(IF(I29=1,0,1)))) -> 0 | D29: =+IF(AND(P29="",Q29=""),1,0) -> 0 | E29: =IF(U29="",1,0) -> 0 | F29: =IF(V29="",1,0) -> 0 | G29: =IF(H29=0,"-",_xlfn.CONCAT(K29,N29,O29,J29)) -> 25010509 | H29: 45662 | I29: 9 | J29: =+IF(I29<10,_xlfn.CONCAT("0",I29),I29) -> 09 | K29: =+YEAR(H29)-2000 -> 25 | L29: =+MONTH(H29) -> 1 | M29: =+DAY(H29) -> 5 | N29: =+IF(L29<10,_xlfn.CONCAT("0",L29),L29) -> 01 | O29: =+IF(M29<10,_xlfn.CONCAT("0",M29),M29) -> 05 | P29: 45800 | T29: CACERES_SALGADO - Fontaneria HARVYN Hernandez aguilar 4 ENERO - Cebolla - | U29: BacC | V29: PGE B31 | W29: Cheque | X29: ×
A30: 25 | B30: =IF(G30="-",0,IF(G29=G30,1,0)) -> 0 | C30: =+IF(G30="-",0,IF(I30=I29+1,0,(IF(I30=1,0,1)))) -> 0 | D30: =+IF(AND(P30="",Q30=""),1,0) -> 0 | E30: =IF(U30="",1,0) -> 0 | F30: =IF(V30="",1,0) -> 0 | G30: =IF(H30=0,"-",_xlfn.CONCAT(K30,N30,O30,J30)) -> 25010510 | H30: 45662 | I30: 10 | J30: =+IF(I30<10,_xlfn.CONCAT("0",I30),I30) -> 10 | K30: =+YEAR(H30)-2000 -> 25 | L30: =+MONTH(H30) -> 1 | M30: =+DAY(H30) -> 5 | N30: =+IF(L30<10,_xlfn.CONCAT("0",L30),L30) -> 01 | O30: =+IF(M30<10,_xlfn.CONCAT("0",M30),M30) -> 05 | P30: 412200 | T30: CACERES_SALGADO - Fontaneria_HARVYN_Hernandez_aguilar_4_ENERO__Cebolla | U30: BacC | V30: PGE B31 | W30: Transferencia | X30: ×
A31: 51 | B31: =IF(G31="-",0,IF(G30=G31,1,0)) -> 0 | C31: =+IF(G31="-",0,IF(I31=I30+1,0,(IF(I31=1,0,1)))) -> 0 | D31: =+IF(AND(P31="",Q31=""),1,0) -> 0 | E31: =IF(U31="",1,0) -> 0 | F31: =IF(V31="",1,0) -> 0 | G31: =IF(H31=0,"-",_xlfn.CONCAT(K31,N31,O31,J31)) -> 25010511 | H31: 45662 | I31: 11 | J31: =+IF(I31<10,_xlfn.CONCAT("0",I31),I31) -> 11 | K31: =+YEAR(H31)-2000 -> 25 | L31: =+MONTH(H31) -> 1 | M31: =+DAY(H31) -> 5 | N31: =+IF(L31<10,_xlfn.CONCAT("0",L31),L31) -> 01 | O31: =+IF(M31<10,_xlfn.CONCAT("0",M31),M31) -> 05 | P31: 132000 | T31: B31 Planilla 31 diciembre al 4 enero - Elvis Adrian Flores Vasquez - Depositar a | U31: BacC | V31: PGE B31 | W31: Transferencia
A32: 52 | B32: =IF(G32="-",0,IF(G31=G32,1,0)) -> 0 | C32: =+IF(G32="-",0,IF(I32=I31+1,0,(IF(I32=1,0,1)))) -> 0 | D32: =+IF(AND(P32="",Q32=""),1,0) -> 0 | E32: =IF(U32="",1,0) -> 0 | F32: =IF(V32="",1,0) -> 0 | G32: =IF(H32=0,"-",_xlfn.CONCAT(K32,N32,O32,J32)) -> 25010512 | H32: 45662 | I32: 12 | J32: =+IF(I32<10,_xlfn.CONCAT("0",I32),I32) -> 12 | K32: =+YEAR(H32)-2000 -> 25 | L32: =+MONTH(H32) -> 1 | M32: =+DAY(H32) -> 5 | N32: =+IF(L32<10,_xlfn.CONCAT("0",L32),L32) -> 01 | O32: =+IF(M32<10,_xlfn.CONCAT("0",M32),M32) -> 05 | P32: 14400 | T32: B31 Planilla 31 diciembre al 4 enero - Elvis Antonio Ramos Dormuz - Depositar a | U32: BacC | V32: PGE B31 | W32: Transferencia
A33: 53 | B33: =IF(G33="-",0,IF(G32=G33,1,0)) -> 0 | C33: =+IF(G33="-",0,IF(I33=I32+1,0,(IF(I33=1,0,1)))) -> 0 | D33: =+IF(AND(P33="",Q33=""),1,0) -> 0 | E33: =IF(U33="",1,0) -> 0 | F33: =IF(V33="",1,0) -> 0 | G33: =IF(H33=0,"-",_xlfn.CONCAT(K33,N33,O33,J33)) -> 25010513 | H33: 45662 | I33: 13 | J33: =+IF(I33<10,_xlfn.CONCAT("0",I33),I33) -> 13 | K33: =+YEAR(H33)-2000 -> 25 | L33: =+MONTH(H33) -> 1 | M33: =+DAY(H33) -> 5 | N33: =+IF(L33<10,_xlfn.CONCAT("0",L33),L33) -> 01 | O33: =+IF(M33<10,_xlfn.CONCAT("0",M33),M33) -> 05 | P33: 20000 | T33: B31 Planilla 31 diciembre al 4 enero - Crispin de Jesús Valencia - Depositar a | U33: BacC | V33: PGE B31 | W33: Transferencia
A34: 54 | B34: =IF(G34="-",0,IF(G33=G34,1,0)) -> 0 | C34: =+IF(G34="-",0,IF(I34=I33+1,0,(IF(I34=1,0,1)))) -> 0 | D34: =+IF(AND(P34="",Q34=""),1,0) -> 0 | E34: =IF(U34="",1,0) -> 0 | F34: =IF(V34="",1,0) -> 0 | G34: =IF(H34=0,"-",_xlfn.CONCAT(K34,N34,O34,J34)) -> 25010514 | H34: 45662 | I34: 14 | J34: =+IF(I34<10,_xlfn.CONCAT("0",I34),I34) -> 14 | K34: =+YEAR(H34)-2000 -> 25 | L34: =+MONTH(H34) -> 1 | M34: =+DAY(H34) -> 5 | N34: =+IF(L34<10,_xlfn.CONCAT("0",L34),L34) -> 01 | O34: =+IF(M34<10,_xlfn.CONCAT("0",M34),M34) -> 05 | P34: 17600 | T34: B31 Planilla 31 diciembre al 4 enero - Francisco Javier Rocha Orozco - Depositar a GRILLO | U34: BacC | V34: PGE B31 | W34: Transferencia
A35: 55 | B35: =IF(G35="-",0,IF(G34=G35,1,0)) -> 0 | C35: =+IF(G35="-",0,IF(I35=I34+1,0,(IF(I35=1,0,1)))) -> 0 | D35: =+IF(AND(P35="",Q35=""),1,0) -> 0 | E35: =IF(U35="",1,0) -> 0 | F35: =IF(V35="",1,0) -> 0 | G35: =IF(H35=0,"-",_xlfn.CONCAT(K35,N35,O35,J35)) -> 25010515 | H35: 45662 | I35: 15 | J35: =+IF(I35<10,_xlfn.CONCAT("0",I35),I35) -> 15 | K35: =+YEAR(H35)-2000 -> 25 | L35: =+MONTH(H35) -> 1 | M35: =+DAY(H35) -> 5 | N35: =+IF(L35<10,_xlfn.CONCAT("0",L35),L35) -> 01 | O35: =+IF(M35<10,_xlfn.CONCAT("0",M35),M35) -> 05 | P35: 108000 | T35: B31 Planilla 31 diciembre al 4 enero - Misael Ramos Dormuz - Depositar a | U35: BacC | V35: PGE B31 | W35: Transferencia
A36: 56 | B36: =IF(G36="-",0,IF(G35=G36,1,0)) -> 0 | C36: =+IF(G36="-",0,IF(I36=I35+1,0,(IF(I36=1,0,1)))) -> 0 | D36: =+IF(AND(P36="",Q36=""),1,0) -> 0 | E36: =IF(U36="",1,0) -> 0 | F36: =IF(V36="",1,0) -> 0 | G36: =IF(H36=0,"-",_xlfn.CONCAT(K36,N36,O36,J36)) -> 25010516 | H36: 45662 | I36: 16 | J36: =+IF(I36<10,_xlfn.CONCAT("0",I36),I36) -> 16 | K36: =+YEAR(H36)-2000 -> 25 | L36: =+MONTH(H36) -> 1 | M36: =+DAY(H36) -> 5 | N36: =+IF(L36<10,_xlfn.CONCAT("0",L36),L36) -> 01 | O36: =+IF(M36<10,_xlfn.CONCAT("0",M36),M36) -> 05 | P36: 14400 | T36: B31 Planilla 31 diciembre al 4 enero - Oscar Manuel Rocha | U36: BacC | V36: PGE B31 | W36: Transferencia
A37: 57 | B37: =IF(G37="-",0,IF(G36=G37,1,0)) -> 0 | C37: =+IF(G37="-",0,IF(I37=I36+1,0,(IF(I37=1,0,1)))) -> 0 | D37: =+IF(AND(P37="",Q37=""),1,0) -> 0 | E37: =IF(U37="",1,0) -> 0 | F37: =IF(V37="",1,0) -> 0 | G37: =IF(H37=0,"-",_xlfn.CONCAT(K37,N37,O37,J37)) -> 25010517 | H37: 45662 | I37: 17 | J37: =+IF(I37<10,_xlfn.CONCAT("0",I37),I37) -> 17 | K37: =+YEAR(H37)-2000 -> 25 | L37: =+MONTH(H37) -> 1 | M37: =+DAY(H37) -> 5 | N37: =+IF(L37<10,_xlfn.CONCAT("0",L37),L37) -> 01 | O37: =+IF(M37<10,_xlfn.CONCAT("0",M37),M37) -> 05 | P37: 14400 | T37: B31 Planilla 31 diciembre al 4 enero - Denis Damian Rocha Orozco | U37: BacC | V37: PGE B31 | W37: Transferencia
A38: 58 | B38: =IF(G38="-",0,IF(G37=G38,1,0)) -> 0 | C38: =+IF(G38="-",0,IF(I38=I37+1,0,(IF(I38=1,0,1)))) -> 0 | D38: =+IF(AND(P38="",Q38=""),1,0) -> 0 | E38: =IF(U38="",1,0) -> 0 | F38: =IF(V38="",1,0) -> 0 | G38: =IF(H38=0,"-",_xlfn.CONCAT(K38,N38,O38,J38)) -> 25010518 | H38: 45662 | I38: 18 | J38: =+IF(I38<10,_xlfn.CONCAT("0",I38),I38) -> 18 | K38: =+YEAR(H38)-2000 -> 25 | L38: =+MONTH(H38) -> 1 | M38: =+DAY(H38) -> 5 | N38: =+IF(L38<10,_xlfn.CONCAT("0",L38),L38) -> 01 | O38: =+IF(M38<10,_xlfn.CONCAT("0",M38),M38) -> 05 | P38: 252000 | T38: B31 Planilla 31 diciembre al 4 enero - EXNER GRILLO | U38: BacC | V38: PGE B31 | W38: Transferencia
A39: 59 | B39: =IF(G39="-",0,IF(G38=G39,1,0)) -> 0 | C39: =+IF(G39="-",0,IF(I39=I38+1,0,(IF(I39=1,0,1)))) -> 0 | D39: =+IF(AND(P39="",Q39=""),1,0) -> 0 | E39: =IF(U39="",1,0) -> 0 | F39: =IF(V39="",1,0) -> 0 | G39: =IF(H39=0,"-",_xlfn.CONCAT(K39,N39,O39,J39)) -> 25010519 | H39: 45662 | I39: 19 | J39: =+IF(I39<10,_xlfn.CONCAT("0",I39),I39) -> 19 | K39: =+YEAR(H39)-2000 -> 25 | L39: =+MONTH(H39) -> 1 | M39: =+DAY(H39) -> 5 | N39: =+IF(L39<10,_xlfn.CONCAT("0",L39),L39) -> 01 | O39: =+IF(M39<10,_xlfn.CONCAT("0",M39),M39) -> 05 | P39: 42000 | T39: B31 Planilla 31 diciembre al 4 enero - EXNER GRILLO feriado | U39: BacC | V39: PGE B31 | W39: Transferencia
A40: 60 | B40: =IF(G40="-",0,IF(G39=G40,1,0)) -> 0 | C40: =+IF(G40="-",0,IF(I40=I39+1,0,(IF(I40=1,0,1)))) -> 0 | D40: =+IF(AND(P40="",Q40=""),1,0) -> 0 | E40: =IF(U40="",1,0) -> 0 | F40: =IF(V40="",1,0) -> 0 | G40: =IF(H40=0,"-",_xlfn.CONCAT(K40,N40,O40,J40)) -> 25010520 | H40: 45662 | I40: 20 | J40: =+IF(I40<10,_xlfn.CONCAT("0",I40),I40) -> 20 | K40: =+YEAR(H40)-2000 -> 25 | L40: =+MONTH(H40) -> 1 | M40: =+DAY(H40) -> 5 | N40: =+IF(L40<10,_xlfn.CONCAT("0",L40),L40) -> 01 | O40: =+IF(M40<10,_xlfn.CONCAT("0",M40),M40) -> 05 | P40: 90000 | T40: B31 Planilla 31 diciembre al 4 enero - EXNER GRILLO viaticos | U40: BacC | V40: PGE B31 | W40: Transferencia
J41: =+IF(I41<10,_xlfn.CONCAT("0",I41),I41) -> 0 | K41: =+YEAR(H41)-2000 -> -100 | L41: =+MONTH(H41) -> 1 | M41: =+DAY(H41) -> 0 | N41: =+IF(L41<10,_xlfn.CONCAT("0",L41),L41) -> 01 | O41: =+IF(M41<10,_xlfn.CONCAT("0",M41),M41) -> 00
A42: 16 | B42: =IF(G42="-",0,IF(G41=G42,1,0)) -> 0 | C42: =+IF(G42="-",0,IF(I42=I41+1,0,(IF(I42=1,0,1)))) -> 1 | D42: =+IF(AND(P42="",Q42=""),1,0) -> 0 | E42: =IF(U42="",1,0) -> 0 | F42: =IF(V42="",1,0) -> 0 | G42: =IF(H42=0,"-",_xlfn.CONCAT(K42,N42,O42,J42)) -> 25010602 | H42: 45663 | I42: 2 | J42: =+IF(I42<10,_xlfn.CONCAT("0",I42),I42) -> 02 | K42: =+YEAR(H42)-2000 -> 25 | L42: =+MONTH(H42) -> 1 | M42: =+DAY(H42) -> 6 | N42: =+IF(L42<10,_xlfn.CONCAT("0",L42),L42) -> 01 | O42: =+IF(M42<10,_xlfn.CONCAT("0",M42),M42) -> 06 | P42: 291349.67 | T42: MAFERCO S.A. - Ref 267707 - Prof 206502 | U42: BacD | V42: PGE B31 | W42: Transferencia | X42: ✓ | Y42: 1046
J43: =+IF(I43<10,_xlfn.CONCAT("0",I43),I43) -> 0 | K43: =+YEAR(H43)-2000 -> -100 | L43: =+MONTH(H43) -> 1 | M43: =+DAY(H43) -> 0 | N43: =+IF(L43<10,_xlfn.CONCAT("0",L43),L43) -> 01 | O43: =+IF(M43<10,_xlfn.CONCAT("0",M43),M43) -> 00
J44: =+IF(I44<10,_xlfn.CONCAT("0",I44),I44) -> 0 | K44: =+YEAR(H44)-2000 -> -100 | L44: =+MONTH(H44) -> 1 | M44: =+DAY(H44) -> 0 | N44: =+IF(L44<10,_xlfn.CONCAT("0",L44),L44) -> 01 | O44: =+IF(M44<10,_xlfn.CONCAT("0",M44),M44) -> 00
J45: =+IF(I45<10,_xlfn.CONCAT("0",I45),I45) -> 0 | K45: =+YEAR(H45)-2000 -> -100 | L45: =+MONTH(H45) -> 1 | M45: =+DAY(H45) -> 0 | N45: =+IF(L45<10,_xlfn.CONCAT("0",L45),L45) -> 01 | O45: =+IF(M45<10,_xlfn.CONCAT("0",M45),M45) -> 00
A46: 31 | B46: =IF(G46="-",0,IF(G45=G46,1,0)) -> 0 | C46: =+IF(G46="-",0,IF(I46=I45+1,0,(IF(I46=1,0,1)))) -> 1 | D46: =+IF(AND(P46="",Q46=""),1,0) -> 0 | E46: =IF(U46="",1,0) -> 0 | F46: =IF(V46="",1,0) -> 0 | G46: =IF(H46=0,"-",_xlfn.CONCAT(K46,N46,O46,J46)) -> 25010606 | H46: 45663 | I46: 6 | J46: =+IF(I46<10,_xlfn.CONCAT("0",I46),I46) -> 06 | K46: =+YEAR(H46)-2000 -> 25 | L46: =+MONTH(H46) -> 1 | M46: =+DAY(H46) -> 6 | N46: =+IF(L46<10,_xlfn.CONCAT("0",L46),L46) -> 01 | O46: =+IF(M46<10,_xlfn.CONCAT("0",M46),M46) -> 06 | P46: 29762.41 | T46: TELECABLE - 8274369 Ref 3607956 PLAYA GRANDE ENERO | U46: BacC | V46: PGE B31 | W46: Transferencia | X46: ✓ | Y46: *0081
J47: =+IF(I47<10,_xlfn.CONCAT("0",I47),I47) -> 0 | K47: =+YEAR(H47)-2000 -> -100 | L47: =+MONTH(H47) -> 1 | M47: =+DAY(H47) -> 0 | N47: =+IF(L47<10,_xlfn.CONCAT("0",L47),L47) -> 01 | O47: =+IF(M47<10,_xlfn.CONCAT("0",M47),M47) -> 00
A48: 36 | B48: =IF(G48="-",0,IF(G47=G48,1,0)) -> 0 | C48: =+IF(G48="-",0,IF(I48=I47+1,0,(IF(I48=1,0,1)))) -> 1 | D48: =+IF(AND(P48="",Q48=""),1,0) -> 0 | E48: =IF(U48="",1,0) -> 0 | F48: =IF(V48="",1,0) -> 0 | G48: =IF(H48=0,"-",_xlfn.CONCAT(K48,N48,O48,J48)) -> 25010608 | H48: 45663 | I48: 8 | J48: =+IF(I48<10,_xlfn.CONCAT("0",I48),I48) -> 08 | K48: =+YEAR(H48)-2000 -> 25 | L48: =+MONTH(H48) -> 1 | M48: =+DAY(H48) -> 6 | N48: =+IF(L48<10,_xlfn.CONCAT("0",L48),L48) -> 01 | O48: =+IF(M48<10,_xlfn.CONCAT("0",M48),M48) -> 06 | P48: 89653.13 | T48: MAFERCO S.A. - Ref 267737 - Cemento x 10 y clavos | U48: Grillo | V48: PGE B31 | W48: Terceros | X48: ✓
A49: 37 | B49: =IF(G49="-",0,IF(G48=G49,1,0)) -> 0 | C49: =+IF(G49="-",0,IF(I49=I48+1,0,(IF(I49=1,0,1)))) -> 0 | D49: =+IF(AND(P49="",Q49=""),1,0) -> 0 | E49: =IF(U49="",1,0) -> 0 | F49: =IF(V49="",1,0) -> 0 | G49: =IF(H49=0,"-",_xlfn.CONCAT(K49,N49,O49,J49)) -> 25010609 | H49: 45663 | I49: 9 | J49: =+IF(I49<10,_xlfn.CONCAT("0",I49),I49) -> 09 | K49: =+YEAR(H49)-2000 -> 25 | L49: =+MONTH(H49) -> 1 | M49: =+DAY(H49) -> 6 | N49: =+IF(L49<10,_xlfn.CONCAT("0",L49),L49) -> 01 | O49: =+IF(M49<10,_xlfn.CONCAT("0",M49),M49) -> 06 | P49: -4948.24 | T49: MAFERCO S.A. NOTA DE CREDITO POR MECHA BLANCA | U49: Grillo | V49: PGE B31 | W49: Terceros | X49: ✓ | Y49: NOTA DE CREDITO
A50: 38 | B50: =IF(G50="-",0,IF(G49=G50,1,0)) -> 0 | C50: =+IF(G50="-",0,IF(I50=I49+1,0,(IF(I50=1,0,1)))) -> 0 | D50: =+IF(AND(P50="",Q50=""),1,0) -> 0 | E50: =IF(U50="",1,0) -> 0 | F50: =IF(V50="",1,0) -> 0 | G50: =IF(H50=0,"-",_xlfn.CONCAT(K50,N50,O50,J50)) -> 25010610 | H50: 45663 | I50: 10 | J50: =+IF(I50<10,_xlfn.CONCAT("0",I50),I50) -> 10 | K50: =+YEAR(H50)-2000 -> 25 | L50: =+MONTH(H50) -> 1 | M50: =+DAY(H50) -> 6 | N50: =+IF(L50<10,_xlfn.CONCAT("0",L50),L50) -> 01 | O50: =+IF(M50<10,_xlfn.CONCAT("0",M50),M50) -> 06 | P50: 95135.87 | T50: CRISTHIAM VASQUEZ RODRIGUEZ - SUPER Y LICORERA REY | U50: Toño | V50: Coyote | W50: Terceros | X50: ✓
J51: =+IF(I51<10,_xlfn.CONCAT("0",I51),I51) -> 0 | K51: =+YEAR(H51)-2000 -> -100 | L51: =+MONTH(H51) -> 1 | M51: =+DAY(H51) -> 0 | N51: =+IF(L51<10,_xlfn.CONCAT("0",L51),L51) -> 01 | O51: =+IF(M51<10,_xlfn.CONCAT("0",M51),M51) -> 00
J52: =+IF(I52<10,_xlfn.CONCAT("0",I52),I52) -> 0 | K52: =+YEAR(H52)-2000 -> -100 | L52: =+MONTH(H52) -> 1 | M52: =+DAY(H52) -> 0 | N52: =+IF(L52<10,_xlfn.CONCAT("0",L52),L52) -> 01 | O52: =+IF(M52<10,_xlfn.CONCAT("0",M52),M52) -> 00
J53: =+IF(I53<10,_xlfn.CONCAT("0",I53),I53) -> 0 | K53: =+YEAR(H53)-2000 -> -100 | L53: =+MONTH(H53) -> 1 | M53: =+DAY(H53) -> 0 | N53: =+IF(L53<10,_xlfn.CONCAT("0",L53),L53) -> 01 | O53: =+IF(M53<10,_xlfn.CONCAT("0",M53),M53) -> 00
A54: 50 | B54: =IF(G54="-",0,IF(G53=G54,1,0)) -> 0 | C54: =+IF(G54="-",0,IF(I54=I53+1,0,(IF(I54=1,0,1)))) -> 1 | D54: =+IF(AND(P54="",Q54=""),1,0) -> 0 | E54: =IF(U54="",1,0) -> 0 | F54: =IF(V54="",1,0) -> 0 | G54: =IF(H54=0,"-",_xlfn.CONCAT(K54,N54,O54,J54)) -> 25010614 | H54: 45663 | I54: 14 | J54: =+IF(I54<10,_xlfn.CONCAT("0",I54),I54) -> 14 | K54: =+YEAR(H54)-2000 -> 25 | L54: =+MONTH(H54) -> 1 | M54: =+DAY(H54) -> 6 | N54: =+IF(L54<10,_xlfn.CONCAT("0",L54),L54) -> 01 | O54: =+IF(M54<10,_xlfn.CONCAT("0",M54),M54) -> 06 | P54: 200000 | T54: Caja Chica B31 - Exner Grillo | U54: BacD | V54: PGE B31 | W54: Transferencia
A55: 263 | B55: =IF(G55="-",0,IF(G54=G55,1,0)) -> 0 | C55: =+IF(G55="-",0,IF(I55=I54+1,0,(IF(I55=1,0,1)))) -> 0 | D55: =+IF(AND(P55="",Q55=""),1,0) -> 0 | E55: =IF(U55="",1,0) -> 0 | F55: =IF(V55="",1,0) -> 0 | G55: =IF(H55=0,"-",_xlfn.CONCAT(K55,N55,O55,J55)) -> 25010615 | H55: 45663 | I55: 15 | J55: =+IF(I55<10,_xlfn.CONCAT("0",I55),I55) -> 15 | K55: =+YEAR(H55)-2000 -> 25 | L55: =+MONTH(H55) -> 1 | M55: =+DAY(H55) -> 6 | N55: =+IF(L55<10,_xlfn.CONCAT("0",L55),L55) -> 01 | O55: =+IF(M55<10,_xlfn.CONCAT("0",M55),M55) -> 06 | P55: 10000 | T55: Combustible - SERVIMOVIL HUACAS S.A (Viaticos Grillo) | U55: Grillo | V55: PGE B31 | W55: Terceros | X55: ✓
A56: 40 | B56: =IF(G56="-",0,IF(G55=G56,1,0)) -> 0 | C56: =+IF(G56="-",0,IF(I56=I55+1,0,(IF(I56=1,0,1)))) -> 0 | D56: =+IF(AND(P56="",Q56=""),1,0) -> 0 | E56: =IF(U56="",1,0) -> 0 | F56: =IF(V56="",1,0) -> 0 | G56: =IF(H56=0,"-",_xlfn.CONCAT(K56,N56,O56,J56)) -> 25010701 | H56: 45664 | I56: 1 | J56: =+IF(I56<10,_xlfn.CONCAT("0",I56),I56) -> 01 | K56: =+YEAR(H56)-2000 -> 25 | L56: =+MONTH(H56) -> 1 | M56: =+DAY(H56) -> 7 | N56: =+IF(L56<10,_xlfn.CONCAT("0",L56),L56) -> 01 | O56: =+IF(M56<10,_xlfn.CONCAT("0",M56),M56) -> 07 | P56: 12657.1 | T56: Almacenes El Colono SA - Huacas - Escoba y bolsa de basura | U56: Grillo | V56: PGE B31 | W56: Terceros | X56: ✓
J57: =+IF(I57<10,_xlfn.CONCAT("0",I57),I57) -> 0 | K57: =+YEAR(H57)-2000 -> -100 | L57: =+MONTH(H57) -> 1 | M57: =+DAY(H57) -> 0 | N57: =+IF(L57<10,_xlfn.CONCAT("0",L57),L57) -> 01 | O57: =+IF(M57<10,_xlfn.CONCAT("0",M57),M57) -> 00
J58: =+IF(I58<10,_xlfn.CONCAT("0",I58),I58) -> 0 | K58: =+YEAR(H58)-2000 -> -100 | L58: =+MONTH(H58) -> 1 | M58: =+DAY(H58) -> 0 | N58: =+IF(L58<10,_xlfn.CONCAT("0",L58),L58) -> 01 | O58: =+IF(M58<10,_xlfn.CONCAT("0",M58),M58) -> 00
A59: 41 | B59: =IF(G59="-",0,IF(G58=G59,1,0)) -> 0 | C59: =+IF(G59="-",0,IF(I59=I58+1,0,(IF(I59=1,0,1)))) -> 1 | D59: =+IF(AND(P59="",Q59=""),1,0) -> 0 | E59: =IF(U59="",1,0) -> 0 | F59: =IF(V59="",1,0) -> 0 | G59: =IF(H59=0,"-",_xlfn.CONCAT(K59,N59,O59,J59)) -> 25010803 | H59: 45665 | I59: 3 | J59: =+IF(I59<10,_xlfn.CONCAT("0",I59),I59) -> 03 | K59: =+YEAR(H59)-2000 -> 25 | L59: =+MONTH(H59) -> 1 | M59: =+DAY(H59) -> 8 | N59: =+IF(L59<10,_xlfn.CONCAT("0",L59),L59) -> 01 | O59: =+IF(M59<10,_xlfn.CONCAT("0",M59),M59) -> 08 | P59: 6539.88 | T59: PVC AMANO LTDA - Mecha c5269,68 + Adaptador c1243 | U59: Grillo | V59: PGE B31 | W59: Terceros | X59: ✓
A60: 42 | B60: =IF(G60="-",0,IF(G59=G60,1,0)) -> 0 | C60: =+IF(G60="-",0,IF(I60=I59+1,0,(IF(I60=1,0,1)))) -> 0 | D60: =+IF(AND(P60="",Q60=""),1,0) -> 0 | E60: =IF(U60="",1,0) -> 0 | F60: =IF(V60="",1,0) -> 0 | G60: =IF(H60=0,"-",_xlfn.CONCAT(K60,N60,O60,J60)) -> 25010804 | H60: 45665 | I60: 4 | J60: =+IF(I60<10,_xlfn.CONCAT("0",I60),I60) -> 04 | K60: =+YEAR(H60)-2000 -> 25 | L60: =+MONTH(H60) -> 1 | M60: =+DAY(H60) -> 8 | N60: =+IF(L60<10,_xlfn.CONCAT("0",L60),L60) -> 01 | O60: =+IF(M60<10,_xlfn.CONCAT("0",M60),M60) -> 08 | P60: 1243 | T60: PVC AMANO LTDA - Union Riego 1243 | U60: Grillo | V60: PGE B31 | W60: Terceros | X60: ✓
A61: 43 | B61: =IF(G61="-",0,IF(G60=G61,1,0)) -> 0 | C61: =+IF(G61="-",0,IF(I61=I60+1,0,(IF(I61=1,0,1)))) -> 0 | D61: =+IF(AND(P61="",Q61=""),1,0) -> 0 | E61: =IF(U61="",1,0) -> 0 | F61: =IF(V61="",1,0) -> 0 | G61: =IF(H61=0,"-",_xlfn.CONCAT(K61,N61,O61,J61)) -> 25010805 | H61: 45665 | I61: 5 | J61: =+IF(I61<10,_xlfn.CONCAT("0",I61),I61) -> 05 | K61: =+YEAR(H61)-2000 -> 25 | L61: =+MONTH(H61) -> 1 | M61: =+DAY(H61) -> 8 | N61: =+IF(L61<10,_xlfn.CONCAT("0",L61),L61) -> 01 | O61: =+IF(M61<10,_xlfn.CONCAT("0",M61),M61) -> 08 | P61: -1243 | T61: PVC AMANO LTDA - NOTA CREDITO POR ADAPTADOR 1243 | U61: Grillo | V61: PGE B31 | W61: Terceros | X61: ✓
J62: =+IF(I62<10,_xlfn.CONCAT("0",I62),I62) -> 0 | K62: =+YEAR(H62)-2000 -> -100 | L62: =+MONTH(H62) -> 1 | M62: =+DAY(H62) -> 0 | N62: =+IF(L62<10,_xlfn.CONCAT("0",L62),L62) -> 01 | O62: =+IF(M62<10,_xlfn.CONCAT("0",M62),M62) -> 00
J63: =+IF(I63<10,_xlfn.CONCAT("0",I63),I63) -> 0 | K63: =+YEAR(H63)-2000 -> -100 | L63: =+MONTH(H63) -> 1 | M63: =+DAY(H63) -> 0 | N63: =+IF(L63<10,_xlfn.CONCAT("0",L63),L63) -> 01 | O63: =+IF(M63<10,_xlfn.CONCAT("0",M63),M63) -> 00
J64: =+IF(I64<10,_xlfn.CONCAT("0",I64),I64) -> 0 | K64: =+YEAR(H64)-2000 -> -100 | L64: =+MONTH(H64) -> 1 | M64: =+DAY(H64) -> 0 | N64: =+IF(L64<10,_xlfn.CONCAT("0",L64),L64) -> 01 | O64: =+IF(M64<10,_xlfn.CONCAT("0",M64),M64) -> 00
A65: 264 | B65: =IF(G65="-",0,IF(G64=G65,1,0)) -> 0 | C65: =+IF(G65="-",0,IF(I65=I64+1,0,(IF(I65=1,0,1)))) -> 1 | D65: =+IF(AND(P65="",Q65=""),1,0) -> 0 | E65: =IF(U65="",1,0) -> 0 | F65: =IF(V65="",1,0) -> 0 | G65: =IF(H65=0,"-",_xlfn.CONCAT(K65,N65,O65,J65)) -> 25010809 | H65: 45665 | I65: 9 | J65: =+IF(I65<10,_xlfn.CONCAT("0",I65),I65) -> 09 | K65: =+YEAR(H65)-2000 -> 25 | L65: =+MONTH(H65) -> 1 | M65: =+DAY(H65) -> 8 | N65: =+IF(L65<10,_xlfn.CONCAT("0",L65),L65) -> 01 | O65: =+IF(M65<10,_xlfn.CONCAT("0",M65),M65) -> 08 | P65: 13000 | T65: Combustible - SERVIMOVIL HUACAS S.A (Grillo) | U65: Grillo | V65: PGE B31 | W65: Terceros | X65: ✓
A66: 389 | B66: =IF(G66="-",0,IF(G65=G66,1,0)) -> 0 | C66: =+IF(G66="-",0,IF(I66=I65+1,0,(IF(I66=1,0,1)))) -> 0 | D66: =+IF(AND(P66="",Q66=""),1,0) -> 0 | E66: =IF(U66="",1,0) -> 0 | F66: =IF(V66="",1,0) -> 0 | G66: =IF(H66=0,"-",_xlfn.CONCAT(K66,N66,O66,J66)) -> 25010810 | H66: 45665 | I66: 10 | J66: =+IF(I66<10,_xlfn.CONCAT("0",I66),I66) -> 10 | K66: =+YEAR(H66)-2000 -> 25 | L66: =+MONTH(H66) -> 1 | M66: =+DAY(H66) -> 8 | N66: =+IF(L66<10,_xlfn.CONCAT("0",L66),L66) -> 01 | O66: =+IF(M66<10,_xlfn.CONCAT("0",M66),M66) -> 08 | P66: 5050 | T66: Restaurante - Alimentos Exclusivos BK CR SA - Nicoya | U66: TC.Prom | V66: Oficina | W66: Tarjeta | X66: ×
J67: =+IF(I67<10,_xlfn.CONCAT("0",I67),I67) -> 0 | K67: =+YEAR(H67)-2000 -> -100 | L67: =+MONTH(H67) -> 1 | M67: =+DAY(H67) -> 0 | N67: =+IF(L67<10,_xlfn.CONCAT("0",L67),L67) -> 01 | O67: =+IF(M67<10,_xlfn.CONCAT("0",M67),M67) -> 00
A68: 47 | B68: =IF(G68="-",0,IF(G67=G68,1,0)) -> 0 | C68: =+IF(G68="-",0,IF(I68=I67+1,0,(IF(I68=1,0,1)))) -> 1 | D68: =+IF(AND(P68="",Q68=""),1,0) -> 0 | E68: =IF(U68="",1,0) -> 0 | F68: =IF(V68="",1,0) -> 0 | G68: =IF(H68=0,"-",_xlfn.CONCAT(K68,N68,O68,J68)) -> 25010902 | H68: 45666 | I68: 2 | J68: =+IF(I68<10,_xlfn.CONCAT("0",I68),I68) -> 02 | K68: =+YEAR(H68)-2000 -> 25 | L68: =+MONTH(H68) -> 1 | M68: =+DAY(H68) -> 9 | N68: =+IF(L68<10,_xlfn.CONCAT("0",L68),L68) -> 01 | O68: =+IF(M68<10,_xlfn.CONCAT("0",M68),M68) -> 09 | P68: 8700.03 | T68: GV FERRETERÍA COYOTE - Guantes | U68: Toño | V68: Coyote | W68: Terceros | X68: ✓
J69: =+IF(I69<10,_xlfn.CONCAT("0",I69),I69) -> 0 | K69: =+YEAR(H69)-2000 -> -100 | L69: =+MONTH(H69) -> 1 | M69: =+DAY(H69) -> 0 | N69: =+IF(L69<10,_xlfn.CONCAT("0",L69),L69) -> 01 | O69: =+IF(M69<10,_xlfn.CONCAT("0",M69),M69) -> 00
A70: 49 | B70: =IF(G70="-",0,IF(G69=G70,1,0)) -> 0 | C70: =+IF(G70="-",0,IF(I70=I69+1,0,(IF(I70=1,0,1)))) -> 0 | D70: =+IF(AND(P70="",Q70=""),1,0) -> 0 | E70: =IF(U70="",1,0) -> 0 | F70: =IF(V70="",1,0) -> 0 | G70: =IF(H70=0,"-",_xlfn.CONCAT(K70,N70,O70,J70)) -> 25011001 | H70: 45667 | I70: 1 | J70: =+IF(I70<10,_xlfn.CONCAT("0",I70),I70) -> 01 | K70: =+YEAR(H70)-2000 -> 25 | L70: =+MONTH(H70) -> 1 | M70: =+DAY(H70) -> 10 | N70: =+IF(L70<10,_xlfn.CONCAT("0",L70),L70) -> 01 | O70: =+IF(M70<10,_xlfn.CONCAT("0",M70),M70) -> 10 | P70: 1378600 | T70: 3-101-912430 SA - Fact 11 - 10 Viajes de tierra + 10h back hoe | U70: No disponible | V70: PGE B31 | W70: Transferencia
J71: =+IF(I71<10,_xlfn.CONCAT("0",I71),I71) -> 0 | K71: =+YEAR(H71)-2000 -> -100 | L71: =+MONTH(H71) -> 1 | M71: =+DAY(H71) -> 0 | N71: =+IF(L71<10,_xlfn.CONCAT("0",L71),L71) -> 01 | O71: =+IF(M71<10,_xlfn.CONCAT("0",M71),M71) -> 00
J72: =+IF(I72<10,_xlfn.CONCAT("0",I72),I72) -> 0 | K72: =+YEAR(H72)-2000 -> -100 | L72: =+MONTH(H72) -> 1 | M72: =+DAY(H72) -> 0 | N72: =+IF(L72<10,_xlfn.CONCAT("0",L72),L72) -> 01 | O72: =+IF(M72<10,_xlfn.CONCAT("0",M72),M72) -> 00
J73: =+IF(I73<10,_xlfn.CONCAT("0",I73),I73) -> 0 | K73: =+YEAR(H73)-2000 -> -100 | L73: =+MONTH(H73) -> 1 | M73: =+DAY(H73) -> 0 | N73: =+IF(L73<10,_xlfn.CONCAT("0",L73),L73) -> 01 | O73: =+IF(M73<10,_xlfn.CONCAT("0",M73),M73) -> 00
A74: 890 | B74: =IF(G74="-",0,IF(G73=G74,1,0)) -> 0 | C74: =+IF(G74="-",0,IF(I74=I73+1,0,(IF(I74=1,0,1)))) -> 1 | D74: =+IF(AND(P74="",Q74=""),1,0) -> 0 | E74: =IF(U74="",1,0) -> 0 | F74: =IF(V74="",1,0) -> 0 | G74: =IF(H74=0,"-",_xlfn.CONCAT(K74,N74,O74,J74)) -> 25011005 | H74: 45667 | I74: 5 | J74: =+IF(I74<10,_xlfn.CONCAT("0",I74),I74) -> 05 | K74: =+YEAR(H74)-2000 -> 25 | L74: =+MONTH(H74) -> 1 | M74: =+DAY(H74) -> 10 | N74: =+IF(L74<10,_xlfn.CONCAT("0",L74),L74) -> 01 | O74: =+IF(M74<10,_xlfn.CONCAT("0",M74),M74) -> 10 | P74: 1638500 | T74: 3-101-912430 SA - Fact10 - 10Viajes de Lastre - 2 Viajes de tierra - 10h Back Hoe | U74: No disponible | V74: PGE B31 | W74: No disponible | X74: ✓
A75: 891 | B75: =IF(G75="-",0,IF(G74=G75,1,0)) -> 0 | C75: =+IF(G75="-",0,IF(I75=I74+1,0,(IF(I75=1,0,1)))) -> 0 | D75: =+IF(AND(P75="",Q75=""),1,0) -> 0 | E75: =IF(U75="",1,0) -> 0 | F75: =IF(V75="",1,0) -> 0 | G75: =IF(H75=0,"-",_xlfn.CONCAT(K75,N75,O75,J75)) -> 25011006 | H75: 45667 | I75: 6 | J75: =+IF(I75<10,_xlfn.CONCAT("0",I75),I75) -> 06 | K75: =+YEAR(H75)-2000 -> 25 | L75: =+MONTH(H75) -> 1 | M75: =+DAY(H75) -> 10 | N75: =+IF(L75<10,_xlfn.CONCAT("0",L75),L75) -> 01 | O75: =+IF(M75<10,_xlfn.CONCAT("0",M75),M75) -> 10 | P75: -1638500 | T75: 3-101-912430 SA - Nota 01 Anula Fact10 - Monto Incorrecto | U75: No disponible | V75: PGE B31 | W75: No disponible | X75: ✓
A76: 69 | B76: =IF(G76="-",0,IF(G75=G76,1,0)) -> 0 | C76: =+IF(G76="-",0,IF(I76=I75+1,0,(IF(I76=1,0,1)))) -> 0 | D76: =+IF(AND(P76="",Q76=""),1,0) -> 0 | E76: =IF(U76="",1,0) -> 0 | F76: =IF(V76="",1,0) -> 0 | G76: =IF(H76=0,"-",_xlfn.CONCAT(K76,N76,O76,J76)) -> 25011101 | H76: 45668 | I76: 1 | J76: =+IF(I76<10,_xlfn.CONCAT("0",I76),I76) -> 01 | K76: =+YEAR(H76)-2000 -> 25 | L76: =+MONTH(H76) -> 1 | M76: =+DAY(H76) -> 11 | N76: =+IF(L76<10,_xlfn.CONCAT("0",L76),L76) -> 01 | O76: =+IF(M76<10,_xlfn.CONCAT("0",M76),M76) -> 11 | P76: 53000 | T76: B31 Planilla 6 al 11 de enero - Geyvin Centeno | U76: BacC | V76: PGE B31 | W76: Transferencia | Y76: g1
A77: 70 | B77: =IF(G77="-",0,IF(G76=G77,1,0)) -> 0 | C77: =+IF(G77="-",0,IF(I77=I76+1,0,(IF(I77=1,0,1)))) -> 0 | D77: =+IF(AND(P77="",Q77=""),1,0) -> 0 | E77: =IF(U77="",1,0) -> 0 | F77: =IF(V77="",1,0) -> 0 | G77: =IF(H77=0,"-",_xlfn.CONCAT(K77,N77,O77,J77)) -> 25011102 | H77: 45668 | I77: 2 | J77: =+IF(I77<10,_xlfn.CONCAT("0",I77),I77) -> 02 | K77: =+YEAR(H77)-2000 -> 25 | L77: =+MONTH(H77) -> 1 | M77: =+DAY(H77) -> 11 | N77: =+IF(L77<10,_xlfn.CONCAT("0",L77),L77) -> 01 | O77: =+IF(M77<10,_xlfn.CONCAT("0",M77),M77) -> 11 | P77: 138000 | T77: B31 Planilla 6 al 11 de enero - Omar Elias Castillo Castillo. DEPOSITA A MARTA PEREZ | U77: BacC | V77: PGE B31 | W77: Transferencia | Y77: g2
A78: 71 | B78: =IF(G78="-",0,IF(G77=G78,1,0)) -> 0 | C78: =+IF(G78="-",0,IF(I78=I77+1,0,(IF(I78=1,0,1)))) -> 0 | D78: =+IF(AND(P78="",Q78=""),1,0) -> 0 | E78: =IF(U78="",1,0) -> 0 | F78: =IF(V78="",1,0) -> 0 | G78: =IF(H78=0,"-",_xlfn.CONCAT(K78,N78,O78,J78)) -> 25011103 | H78: 45668 | I78: 3 | J78: =+IF(I78<10,_xlfn.CONCAT("0",I78),I78) -> 03 | K78: =+YEAR(H78)-2000 -> 25 | L78: =+MONTH(H78) -> 1 | M78: =+DAY(H78) -> 11 | N78: =+IF(L78<10,_xlfn.CONCAT("0",L78),L78) -> 01 | O78: =+IF(M78<10,_xlfn.CONCAT("0",M78),M78) -> 11 | P78: 132000 | T78: B31 Planilla 6 al 11 de enero - Eliecer Leonardo Lacayo | U78: BacC | V78: PGE B31 | W78: Transferencia | Y78: g3
A79: 72 | B79: =IF(G79="-",0,IF(G78=G79,1,0)) -> 0 | C79: =+IF(G79="-",0,IF(I79=I78+1,0,(IF(I79=1,0,1)))) -> 0 | D79: =+IF(AND(P79="",Q79=""),1,0) -> 0 | E79: =IF(U79="",1,0) -> 0 | F79: =IF(V79="",1,0) -> 0 | G79: =IF(H79=0,"-",_xlfn.CONCAT(K79,N79,O79,J79)) -> 25011104 | H79: 45668 | I79: 4 | J79: =+IF(I79<10,_xlfn.CONCAT("0",I79),I79) -> 04 | K79: =+YEAR(H79)-2000 -> 25 | L79: =+MONTH(H79) -> 1 | M79: =+DAY(H79) -> 11 | N79: =+IF(L79<10,_xlfn.CONCAT("0",L79),L79) -> 01 | O79: =+IF(M79<10,_xlfn.CONCAT("0",M79),M79) -> 11 | P79: 132000 | T79: B31 Planilla 6 al 11 de enero - Freddy Antonio Hernandez | U79: BacC | V79: PGE B31 | W79: Transferencia | Y79: g4
A80: 73 | B80: =IF(G80="-",0,IF(G79=G80,1,0)) -> 0 | C80: =+IF(G80="-",0,IF(I80=I79+1,0,(IF(I80=1,0,1)))) -> 0 | D80: =+IF(AND(P80="",Q80=""),1,0) -> 0 | E80: =IF(U80="",1,0) -> 0 | F80: =IF(V80="",1,0) -> 0 | G80: =IF(H80=0,"-",_xlfn.CONCAT(K80,N80,O80,J80)) -> 25011105 | H80: 45668 | I80: 5 | J80: =+IF(I80<10,_xlfn.CONCAT("0",I80),I80) -> 05 | K80: =+YEAR(H80)-2000 -> 25 | L80: =+MONTH(H80) -> 1 | M80: =+DAY(H80) -> 11 | N80: =+IF(L80<10,_xlfn.CONCAT("0",L80),L80) -> 01 | O80: =+IF(M80<10,_xlfn.CONCAT("0",M80),M80) -> 11 | P80: 159000 | T80: B31 Planilla 6 al 11 de enero - Michael Medina Corea | U80: BacC | V80: PGE B31 | W80: Transferencia | Y80: g5
A81: 74 | B81: =IF(G81="-",0,IF(G80=G81,1,0)) -> 0 | C81: =+IF(G81="-",0,IF(I81=I80+1,0,(IF(I81=1,0,1)))) -> 0 | D81: =+IF(AND(P81="",Q81=""),1,0) -> 0 | E81: =IF(U81="",1,0) -> 0 | F81: =IF(V81="",1,0) -> 0 | G81: =IF(H81=0,"-",_xlfn.CONCAT(K81,N81,O81,J81)) -> 25011106 | H81: 45668 | I81: 6 | J81: =+IF(I81<10,_xlfn.CONCAT("0",I81),I81) -> 06 | K81: =+YEAR(H81)-2000 -> 25 | L81: =+MONTH(H81) -> 1 | M81: =+DAY(H81) -> 11 | N81: =+IF(L81<10,_xlfn.CONCAT("0",L81),L81) -> 01 | O81: =+IF(M81<10,_xlfn.CONCAT("0",M81),M81) -> 11 | P81: 132000 | T81: B31 Planilla 6 al 11 de enero - Elvis Adrian Flores Vasquez - Depositar a | U81: BacC | V81: PGE B31 | W81: Transferencia
A82: 75 | B82: =IF(G82="-",0,IF(G81=G82,1,0)) -> 0 | C82: =+IF(G82="-",0,IF(I82=I81+1,0,(IF(I82=1,0,1)))) -> 0 | D82: =+IF(AND(P82="",Q82=""),1,0) -> 0 | E82: =IF(U82="",1,0) -> 0 | F82: =IF(V82="",1,0) -> 0 | G82: =IF(H82=0,"-",_xlfn.CONCAT(K82,N82,O82,J82)) -> 25011107 | H82: 45668 | I82: 7 | J82: =+IF(I82<10,_xlfn.CONCAT("0",I82),I82) -> 07 | K82: =+YEAR(H82)-2000 -> 25 | L82: =+MONTH(H82) -> 1 | M82: =+DAY(H82) -> 11 | N82: =+IF(L82<10,_xlfn.CONCAT("0",L82),L82) -> 01 | O82: =+IF(M82<10,_xlfn.CONCAT("0",M82),M82) -> 11 | P82: 108000 | T82: B31 Planilla 6 al 11 de enero - Misael Ramos Dormuz - Depositar a | U82: BacC | V82: PGE B31 | W82: Transferencia
A83: 76 | B83: =IF(G83="-",0,IF(G82=G83,1,0)) -> 0 | C83: =+IF(G83="-",0,IF(I83=I82+1,0,(IF(I83=1,0,1)))) -> 0 | D83: =+IF(AND(P83="",Q83=""),1,0) -> 0 | E83: =IF(U83="",1,0) -> 0 | F83: =IF(V83="",1,0) -> 0 | G83: =IF(H83=0,"-",_xlfn.CONCAT(K83,N83,O83,J83)) -> 25011108 | H83: 45668 | I83: 8 | J83: =+IF(I83<10,_xlfn.CONCAT("0",I83),I83) -> 08 | K83: =+YEAR(H83)-2000 -> 25 | L83: =+MONTH(H83) -> 1 | M83: =+DAY(H83) -> 11 | N83: =+IF(L83<10,_xlfn.CONCAT("0",L83),L83) -> 01 | O83: =+IF(M83<10,_xlfn.CONCAT("0",M83),M83) -> 11 | P83: 252000 | T83: B31 Planilla 6 al 11 de enero - EXNER GRILLO | U83: BacC | V83: PGE B31 | W83: Transferencia
A84: 77 | B84: =IF(G84="-",0,IF(G83=G84,1,0)) -> 0 | C84: =+IF(G84="-",0,IF(I84=I83+1,0,(IF(I84=1,0,1)))) -> 0 | D84: =+IF(AND(P84="",Q84=""),1,0) -> 0 | E84: =IF(U84="",1,0) -> 0 | F84: =IF(V84="",1,0) -> 0 | G84: =IF(H84=0,"-",_xlfn.CONCAT(K84,N84,O84,J84)) -> 25011109 | H84: 45668 | I84: 9 | J84: =+IF(I84<10,_xlfn.CONCAT("0",I84),I84) -> 09 | K84: =+YEAR(H84)-2000 -> 25 | L84: =+MONTH(H84) -> 1 | M84: =+DAY(H84) -> 11 | N84: =+IF(L84<10,_xlfn.CONCAT("0",L84),L84) -> 01 | O84: =+IF(M84<10,_xlfn.CONCAT("0",M84),M84) -> 11 | P84: 90000 | T84: B31 Planilla 6 al 11 de enero - EXNER GRILLO viaticos | U84: BacC | V84: PGE B31 | W84: Transferencia
A85: 78 | B85: =IF(G85="-",0,IF(G84=G85,1,0)) -> 0 | C85: =+IF(G85="-",0,IF(I85=I84+1,0,(IF(I85=1,0,1)))) -> 0 | D85: =+IF(AND(P85="",Q85=""),1,0) -> 0 | E85: =IF(U85="",1,0) -> 0 | F85: =IF(V85="",1,0) -> 0 | G85: =IF(H85=0,"-",_xlfn.CONCAT(K85,N85,O85,J85)) -> 25011110 | H85: 45668 | I85: 10 | J85: =+IF(I85<10,_xlfn.CONCAT("0",I85),I85) -> 10 | K85: =+YEAR(H85)-2000 -> 25 | L85: =+MONTH(H85) -> 1 | M85: =+DAY(H85) -> 11 | N85: =+IF(L85<10,_xlfn.CONCAT("0",L85),L85) -> 01 | O85: =+IF(M85<10,_xlfn.CONCAT("0",M85),M85) -> 11 | P85: 150000 | T85: B31 11 enero EXNER GRILLO - Comida | U85: BacC | V85: PGE B31 | W85: Transferencia | Y85: g6
A86: 79 | B86: =IF(G86="-",0,IF(G85=G86,1,0)) -> 0 | C86: =+IF(G86="-",0,IF(I86=I85+1,0,(IF(I86=1,0,1)))) -> 0 | D86: =+IF(AND(P86="",Q86=""),1,0) -> 0 | E86: =IF(U86="",1,0) -> 0 | F86: =IF(V86="",1,0) -> 0 | G86: =IF(H86=0,"-",_xlfn.CONCAT(K86,N86,O86,J86)) -> 25011111 | H86: 45668 | I86: 11 | J86: =+IF(I86<10,_xlfn.CONCAT("0",I86),I86) -> 11 | K86: =+YEAR(H86)-2000 -> 25 | L86: =+MONTH(H86) -> 1 | M86: =+DAY(H86) -> 11 | N86: =+IF(L86<10,_xlfn.CONCAT("0",L86),L86) -> 01 | O86: =+IF(M86<10,_xlfn.CONCAT("0",M86),M86) -> 11 | P86: 30000 | T86: Wagner Zepeda Bustos [8770-8682] viaje maferco y grupo diez | U86: BacC | V86: PGE B31 | W86: SINPE Movil | Y86: g7
A87: 80 | B87: =IF(G87="-",0,IF(G86=G87,1,0)) -> 0 | C87: =+IF(G87="-",0,IF(I87=I86+1,0,(IF(I87=1,0,1)))) -> 0 | D87: =+IF(AND(P87="",Q87=""),1,0) -> 0 | E87: =IF(U87="",1,0) -> 0 | F87: =IF(V87="",1,0) -> 0 | G87: =IF(H87=0,"-",_xlfn.CONCAT(K87,N87,O87,J87)) -> 25011112 | H87: 45668 | I87: 12 | J87: =+IF(I87<10,_xlfn.CONCAT("0",I87),I87) -> 12 | K87: =+YEAR(H87)-2000 -> 25 | L87: =+MONTH(H87) -> 1 | M87: =+DAY(H87) -> 11 | N87: =+IF(L87<10,_xlfn.CONCAT("0",L87),L87) -> 01 | O87: =+IF(M87<10,_xlfn.CONCAT("0",M87),M87) -> 11 | P87: 12426 | T87: MAFERCO S.A. - Fact 104245 Prof ***** | U87: Grillo | V87: PGE B31 | W87: Terceros | X87: ✓
A88: 81 | B88: =IF(G88="-",0,IF(G87=G88,1,0)) -> 0 | C88: =+IF(G88="-",0,IF(I88=I87+1,0,(IF(I88=1,0,1)))) -> 0 | D88: =+IF(AND(P88="",Q88=""),1,0) -> 0 | E88: =IF(U88="",1,0) -> 0 | F88: =IF(V88="",1,0) -> 0 | G88: =IF(H88=0,"-",_xlfn.CONCAT(K88,N88,O88,J88)) -> 25011113 | H88: 45668 | I88: 13 | J88: =+IF(I88<10,_xlfn.CONCAT("0",I88),I88) -> 13 | K88: =+YEAR(H88)-2000 -> 25 | L88: =+MONTH(H88) -> 1 | M88: =+DAY(H88) -> 11 | N88: =+IF(L88<10,_xlfn.CONCAT("0",L88),L88) -> 01 | O88: =+IF(M88<10,_xlfn.CONCAT("0",M88),M88) -> 11 | P88: 271293.01 | T88: MAFERCO S.A. - Fact 104198 - Prof 208137 - Varilla Cemento Alambre | U88: Grillo | V88: PGE B31 | W88: Terceros | X88: ✓
A89: 82 | B89: =IF(G89="-",0,IF(G88=G89,1,0)) -> 0 | C89: =+IF(G89="-",0,IF(I89=I88+1,0,(IF(I89=1,0,1)))) -> 0 | D89: =+IF(AND(P89="",Q89=""),1,0) -> 0 | E89: =IF(U89="",1,0) -> 0 | F89: =IF(V89="",1,0) -> 0 | G89: =IF(H89=0,"-",_xlfn.CONCAT(K89,N89,O89,J89)) -> 25011114 | H89: 45668 | I89: 14 | J89: =+IF(I89<10,_xlfn.CONCAT("0",I89),I89) -> 14 | K89: =+YEAR(H89)-2000 -> 25 | L89: =+MONTH(H89) -> 1 | M89: =+DAY(H89) -> 11 | N89: =+IF(L89<10,_xlfn.CONCAT("0",L89),L89) -> 01 | O89: =+IF(M89<10,_xlfn.CONCAT("0",M89),M89) -> 11 | P89: 56161 | T89: SUPLIDORA HUACAS LTDA - Cable THHN | U89: Grillo | V89: PGE B31 | W89: Terceros | X89: ✓
J90: =+IF(I90<10,_xlfn.CONCAT("0",I90),I90) -> 0 | K90: =+YEAR(H90)-2000 -> -100 | L90: =+MONTH(H90) -> 1 | M90: =+DAY(H90) -> 0 | N90: =+IF(L90<10,_xlfn.CONCAT("0",L90),L90) -> 01 | O90: =+IF(M90<10,_xlfn.CONCAT("0",M90),M90) -> 00
A91: 92 | B91: =IF(G91="-",0,IF(G90=G91,1,0)) -> 0 | C91: =+IF(G91="-",0,IF(I91=I90+1,0,(IF(I91=1,0,1)))) -> 1 | D91: =+IF(AND(P91="",Q91=""),1,0) -> 0 | E91: =IF(U91="",1,0) -> 1 | F91: =IF(V91="",1,0) -> 0 | G91: =IF(H91=0,"-",_xlfn.CONCAT(K91,N91,O91,J91)) -> 25011116 | H91: 45668 | I91: 16 | J91: =+IF(I91<10,_xlfn.CONCAT("0",I91),I91) -> 16 | K91: =+YEAR(H91)-2000 -> 25 | L91: =+MONTH(H91) -> 1 | M91: =+DAY(H91) -> 11 | N91: =+IF(L91<10,_xlfn.CONCAT("0",L91),L91) -> 01 | O91: =+IF(M91<10,_xlfn.CONCAT("0",M91),M91) -> 11 | P91: 541388.65 | T91: SUPLIDORA HUACAS LTDA - Ref106980 Prof 82013 - Material electrico | V91: PGE B31 | W91: Transferencia | X91: ✓ | Y91: 5 mil con tarjeta
J92: =+IF(I92<10,_xlfn.CONCAT("0",I92),I92) -> 0 | K92: =+YEAR(H92)-2000 -> -100 | L92: =+MONTH(H92) -> 1 | M92: =+DAY(H92) -> 0 | N92: =+IF(L92<10,_xlfn.CONCAT("0",L92),L92) -> 01 | O92: =+IF(M92<10,_xlfn.CONCAT("0",M92),M92) -> 00
J93: =+IF(I93<10,_xlfn.CONCAT("0",I93),I93) -> 0 | K93: =+YEAR(H93)-2000 -> -100 | L93: =+MONTH(H93) -> 1 | M93: =+DAY(H93) -> 0 | N93: =+IF(L93<10,_xlfn.CONCAT("0",L93),L93) -> 01 | O93: =+IF(M93<10,_xlfn.CONCAT("0",M93),M93) -> 00
J94: =+IF(I94<10,_xlfn.CONCAT("0",I94),I94) -> 0 | K94: =+YEAR(H94)-2000 -> -100 | L94: =+MONTH(H94) -> 1 | M94: =+DAY(H94) -> 0 | N94: =+IF(L94<10,_xlfn.CONCAT("0",L94),L94) -> 01 | O94: =+IF(M94<10,_xlfn.CONCAT("0",M94),M94) -> 00
J95: =+IF(I95<10,_xlfn.CONCAT("0",I95),I95) -> 0 | K95: =+YEAR(H95)-2000 -> -100 | L95: =+MONTH(H95) -> 1 | M95: =+DAY(H95) -> 0 | N95: =+IF(L95<10,_xlfn.CONCAT("0",L95),L95) -> 01 | O95: =+IF(M95<10,_xlfn.CONCAT("0",M95),M95) -> 00
J96: =+IF(I96<10,_xlfn.CONCAT("0",I96),I96) -> 0 | K96: =+YEAR(H96)-2000 -> -100 | L96: =+MONTH(H96) -> 1 | M96: =+DAY(H96) -> 0 | N96: =+IF(L96<10,_xlfn.CONCAT("0",L96),L96) -> 01 | O96: =+IF(M96<10,_xlfn.CONCAT("0",M96),M96) -> 00
A97: 88 | B97: =IF(G97="-",0,IF(G96=G97,1,0)) -> 0 | C97: =+IF(G97="-",0,IF(I97=I96+1,0,(IF(I97=1,0,1)))) -> 0 | D97: =+IF(AND(P97="",Q97=""),1,0) -> 0 | E97: =IF(U97="",1,0) -> 1 | F97: =IF(V97="",1,0) -> 0 | G97: =IF(H97=0,"-",_xlfn.CONCAT(K97,N97,O97,J97)) -> 25011301 | H97: 45670 | I97: 1 | J97: =+IF(I97<10,_xlfn.CONCAT("0",I97),I97) -> 01 | K97: =+YEAR(H97)-2000 -> 25 | L97: =+MONTH(H97) -> 1 | M97: =+DAY(H97) -> 13 | N97: =+IF(L97<10,_xlfn.CONCAT("0",L97),L97) -> 01 | O97: =+IF(M97<10,_xlfn.CONCAT("0",M97),M97) -> 13 | P97: 193446.11 | T97: MAFERCO S.A. - Fact 104491 Prof 208690 | V97: PGE B31 | X97: ✓
A98: 89 | B98: =IF(G98="-",0,IF(G97=G98,1,0)) -> 0 | C98: =+IF(G98="-",0,IF(I98=I97+1,0,(IF(I98=1,0,1)))) -> 0 | D98: =+IF(AND(P98="",Q98=""),1,0) -> 0 | E98: =IF(U98="",1,0) -> 0 | F98: =IF(V98="",1,0) -> 0 | G98: =IF(H98=0,"-",_xlfn.CONCAT(K98,N98,O98,J98)) -> 25011302 | H98: 45670 | I98: 2 | J98: =+IF(I98<10,_xlfn.CONCAT("0",I98),I98) -> 02 | K98: =+YEAR(H98)-2000 -> 25 | L98: =+MONTH(H98) -> 1 | M98: =+DAY(H98) -> 13 | N98: =+IF(L98<10,_xlfn.CONCAT("0",L98),L98) -> 01 | O98: =+IF(M98<10,_xlfn.CONCAT("0",M98),M98) -> 13 | P98: 35028.82 | T98: MAFERCO S.A. - Fact 104492 Prof 208312 - Manómetro | U98: BacC | V98: PGE B31 | W98: Transferencia | X98: ✓
A99: 90 | B99: =IF(G99="-",0,IF(G98=G99,1,0)) -> 0 | C99: =+IF(G99="-",0,IF(I99=I98+1,0,(IF(I99=1,0,1)))) -> 0 | D99: =+IF(AND(P99="",Q99=""),1,0) -> 0 | E99: =IF(U99="",1,0) -> 0 | F99: =IF(V99="",1,0) -> 0 | G99: =IF(H99=0,"-",_xlfn.CONCAT(K99,N99,O99,J99)) -> 25011303 | H99: 45670 | I99: 3 | J99: =+IF(I99<10,_xlfn.CONCAT("0",I99),I99) -> 03 | K99: =+YEAR(H99)-2000 -> 25 | L99: =+MONTH(H99) -> 1 | M99: =+DAY(H99) -> 13 | N99: =+IF(L99<10,_xlfn.CONCAT("0",L99),L99) -> 01 | O99: =+IF(M99<10,_xlfn.CONCAT("0",M99),M99) -> 13 | P99: 7601.51 | T99: GV FERRETERÍA COYOTE - Pegamento PVC | U99: Toño | V99: Coyote | W99: Efectivo | X99: ✓
J100: =+IF(I100<10,_xlfn.CONCAT("0",I100),I100) -> 0 | K100: =+YEAR(H100)-2000 -> -100 | L100: =+MONTH(H100) -> 1 | M100: =+DAY(H100) -> 0 | N100: =+IF(L100<10,_xlfn.CONCAT("0",L100),L100) -> 01 | O100: =+IF(M100<10,_xlfn.CONCAT("0",M100),M100) -> 00
J101: =+IF(I101<10,_xlfn.CONCAT("0",I101),I101) -> 0 | K101: =+YEAR(H101)-2000 -> -100 | L101: =+MONTH(H101) -> 1 | M101: =+DAY(H101) -> 0 | N101: =+IF(L101<10,_xlfn.CONCAT("0",L101),L101) -> 01 | O101: =+IF(M101<10,_xlfn.CONCAT("0",M101),M101) -> 00
...
